Workbook

Sheet Filas
A1: Filas | B1: Áreas Transaccionales Filas No. | C1: Áreas Transaccionales Filas Descripción | D1: Codigo Transacción Filas | E1: Transacción filas | F1: Código Productos (CUP) | G1: Productos (CUP) | H1: Código CPC Grupos | I1: CPC Grupos | J1: Código Productos Compactos | K1: Productos Compactos | L1: Código Bioeconomía Productos | M1: Bioeconomía Productos | N1: Código CUPc | O1: CUPc
A2: mp_f001 | B2: ATF01 | C2: Producción | D2: P1 | E2: Producción | F2: 1 | G2: Trigo | H2: =IF(F2="","",VLOOKUP(F2,Productos!$A$2:$F$182,3,FALSE)) -> 0 | I2: =IF(F2="","",VLOOKUP(F2,Productos!$A$2:$F$182,4,FALSE)) -> Productos de la agricultura, la silvicultura y la pesca | J2: =IF(F2="","",VLOOKUP(F2,Productos!$A$2:$F$182,5,FALSE)) -> 1 | K2: =IF(F2="","",VLOOKUP(F2,Productos!$A$2:$F$182,6,FALSE)) -> Agropecuarios | L2: 1 | M2: Bioeconomía | N2: =VLOOKUP(F2,Productos!$A$2:$J$182,5) -> 1 | O2: =VLOOKUP(F2,Productos!$A$2:$J$182,6) -> Agropecuarios
A3: mp_f002 | B3: ATF01 | C3: Producción | D3: P1 | E3: Producción | F3: 2 | G3: Maíz | H3: =IF(F3="","",VLOOKUP(F3,Productos!$A$2:$F$182,3,FALSE)) -> 0 | I3: =IF(F3="","",VLOOKUP(F3,Productos!$A$2:$F$182,4,FALSE)) -> Productos de la agricultura, la silvicultura y la pesca | J3: =IF(F3="","",VLOOKUP(F3,Productos!$A$2:$F$182,5,FALSE)) -> 1 | K3: =IF(F3="","",VLOOKUP(F3,Productos!$A$2:$F$182,6,FALSE)) -> Agropecuarios | L3: 1 | M3: Bioeconomía | N3: =VLOOKUP(F3,Productos!$A$2:$J$182,5) -> 1 | O3: =VLOOKUP(F3,Productos!$A$2:$J$182,6) -> Agropecuarios
A4: mp_f003 | B4: ATF01 | C4: Producción | D4: P1 | E4: Producción | F4: 3 | G4: Otros cereales | H4: =IF(F4="","",VLOOKUP(F4,Productos!$A$2:$F$182,3,FALSE)) -> 0 | I4: =IF(F4="","",VLOOKUP(F4,Productos!$A$2:$F$182,4,FALSE)) -> Productos de la agricultura, la silvicultura y la pesca | J4: =IF(F4="","",VLOOKUP(F4,Productos!$A$2:$F$182,5,FALSE)) -> 1 | K4: =IF(F4="","",VLOOKUP(F4,Productos!$A$2:$F$182,6,FALSE)) -> Agropecuarios | L4: 1 | M4: Bioeconomía | N4: =VLOOKUP(F4,Productos!$A$2:$J$182,5) -> 1 | O4: =VLOOKUP(F4,Productos!$A$2:$J$182,6) -> Agropecuarios
A5: mp_f004 | B5: ATF01 | C5: Producción | D5: P1 | E5: Producción | F5: 4 | G5: Tubérculos y legumbres | H5: =IF(F5="","",VLOOKUP(F5,Productos!$A$2:$F$182,3,FALSE)) -> 0 | I5: =IF(F5="","",VLOOKUP(F5,Productos!$A$2:$F$182,4,FALSE)) -> Productos de la agricultura, la silvicultura y la pesca | J5: =IF(F5="","",VLOOKUP(F5,Productos!$A$2:$F$182,5,FALSE)) -> 1 | K5: =IF(F5="","",VLOOKUP(F5,Productos!$A$2:$F$182,6,FALSE)) -> Agropecuarios | L5: 1 | M5: Bioeconomía | N5: =VLOOKUP(F5,Productos!$A$2:$J$182,5) -> 1 | O5: =VLOOKUP(F5,Productos!$A$2:$J$182,6) -> Agropecuarios
A6: mp_f005 | B6: ATF01 | C6: Producción | D6: P1 | E6: Producción | F6: 5 | G6: Forrajeras y otros cultivos de uso industrial | H6: =IF(F6="","",VLOOKUP(F6,Productos!$A$2:$F$182,3,FALSE)) -> 0 | I6: =IF(F6="","",VLOOKUP(F6,Productos!$A$2:$F$182,4,FALSE)) -> Productos de la agricultura, la silvicultura y la pesca | J6: =IF(F6="","",VLOOKUP(F6,Productos!$A$2:$F$182,5,FALSE)) -> 1 | K6: =IF(F6="","",VLOOKUP(F6,Productos!$A$2:$F$182,6,FALSE)) -> Agropecuarios | L6: 1 | M6: Bioeconomía | N6: =VLOOKUP(F6,Productos!$A$2:$J$182,5) -> 1 | O6: =VLOOKUP(F6,Productos!$A$2:$J$182,6) -> Agropecuarios
A7: mp_f006 | B7: ATF01 | C7: Producción | D7: P1 | E7: Producción | F7: 6 | G7: Hortalizas y setas | H7: =IF(F7="","",VLOOKUP(F7,Productos!$A$2:$F$182,3,FALSE)) -> 0 | I7: =IF(F7="","",VLOOKUP(F7,Productos!$A$2:$F$182,4,FALSE)) -> Productos de la agricultura, la silvicultura y la pesca | J7: =IF(F7="","",VLOOKUP(F7,Productos!$A$2:$F$182,5,FALSE)) -> 1 | K7: =IF(F7="","",VLOOKUP(F7,Productos!$A$2:$F$182,6,FALSE)) -> Agropecuarios | L7: 1 | M7: Bioeconomía | N7: =VLOOKUP(F7,Productos!$A$2:$J$182,5) -> 1 | O7: =VLOOKUP(F7,Productos!$A$2:$J$182,6) -> Agropecuarios
A8: mp_f007 | B8: ATF01 | C8: Producción | D8: P1 | E8: Producción | F8: 7 | G8: Uva vinífera y pisquera | H8: =IF(F8="","",VLOOKUP(F8,Productos!$A$2:$F$182,3,FALSE)) -> 0 | I8: =IF(F8="","",VLOOKUP(F8,Productos!$A$2:$F$182,4,FALSE)) -> Productos de la agricultura, la silvicultura y la pesca | J8: =IF(F8="","",VLOOKUP(F8,Productos!$A$2:$F$182,5,FALSE)) -> 1 | K8: =IF(F8="","",VLOOKUP(F8,Productos!$A$2:$F$182,6,FALSE)) -> Agropecuarios | L8: 1 | M8: Bioeconomía | N8: =VLOOKUP(F8,Productos!$A$2:$J$182,5) -> 1 | O8: =VLOOKUP(F8,Productos!$A$2:$J$182,6) -> Agropecuarios
A9: mp_f008 | B9: ATF01 | C9: Producción | D9: P1 | E9: Producción | F9: 8 | G9: Uva de mesa | H9: =IF(F9="","",VLOOKUP(F9,Productos!$A$2:$F$182,3,FALSE)) -> 0 | I9: =IF(F9="","",VLOOKUP(F9,Productos!$A$2:$F$182,4,FALSE)) -> Productos de la agricultura, la silvicultura y la pesca | J9: =IF(F9="","",VLOOKUP(F9,Productos!$A$2:$F$182,5,FALSE)) -> 1 | K9: =IF(F9="","",VLOOKUP(F9,Productos!$A$2:$F$182,6,FALSE)) -> Agropecuarios | L9: 1 | M9: Bioeconomía | N9: =VLOOKUP(F9,Productos!$A$2:$J$182,5) -> 1 | O9: =VLOOKUP(F9,Productos!$A$2:$J$182,6) -> Agropecuarios
A10: mp_f009 | B10: ATF01 | C10: Producción | D10: P1 | E10: Producción | F10: 9 | G10: Manzanas | H10: =IF(F10="","",VLOOKUP(F10,Productos!$A$2:$F$182,3,FALSE)) -> 0 | I10: =IF(F10="","",VLOOKUP(F10,Productos!$A$2:$F$182,4,FALSE)) -> Productos de la agricultura, la silvicultura y la pesca | J10: =IF(F10="","",VLOOKUP(F10,Productos!$A$2:$F$182,5,FALSE)) -> 1 | K10: =IF(F10="","",VLOOKUP(F10,Productos!$A$2:$F$182,6,FALSE)) -> Agropecuarios | L10: 1 | M10: Bioeconomía | N10: =VLOOKUP(F10,Productos!$A$2:$J$182,5) -> 1 | O10: =VLOOKUP(F10,Productos!$A$2:$J$182,6) -> Agropecuarios
A11: mp_f010 | B11: ATF01 | C11: Producción | D11: P1 | E11: Producción | F11: 10 | G11: Duraznos y otros carozos | H11: =IF(F11="","",VLOOKUP(F11,Productos!$A$2:$F$182,3,FALSE)) -> 0 | I11: =IF(F11="","",VLOOKUP(F11,Productos!$A$2:$F$182,4,FALSE)) -> Productos de la agricultura, la silvicultura y la pesca | J11: =IF(F11="","",VLOOKUP(F11,Productos!$A$2:$F$182,5,FALSE)) -> 1 | K11: =IF(F11="","",VLOOKUP(F11,Productos!$A$2:$F$182,6,FALSE)) -> Agropecuarios | L11: 1 | M11: Bioeconomía | N11: =VLOOKUP(F11,Productos!$A$2:$J$182,5) -> 1 | O11: =VLOOKUP(F11,Productos!$A$2:$J$182,6) -> Agropecuarios
A12: mp_f011 | B12: ATF01 | C12: Producción | D12: P1 | E12: Producción | F12: 11 | G12: Paltas | H12: =IF(F12="","",VLOOKUP(F12,Productos!$A$2:$F$182,3,FALSE)) -> 0 | I12: =IF(F12="","",VLOOKUP(F12,Productos!$A$2:$F$182,4,FALSE)) -> Productos de la agricultura, la silvicultura y la pesca | J12: =IF(F12="","",VLOOKUP(F12,Productos!$A$2:$F$182,5,FALSE)) -> 1 | K12: =IF(F12="","",VLOOKUP(F12,Productos!$A$2:$F$182,6,FALSE)) -> Agropecuarios | L12: 1 | M12: Bioeconomía | N12: =VLOOKUP(F12,Productos!$A$2:$J$182,5) -> 1 | O12: =VLOOKUP(F12,Productos!$A$2:$J$182,6) -> Agropecuarios
A13: mp_f012 | B13: ATF01 | C13: Producción | D13: P1 | E13: Producción | F13: 12 | G13: Kiwis y otras frutas tropicales | H13: =IF(F13="","",VLOOKUP(F13,Productos!$A$2:$F$182,3,FALSE)) -> 0 | I13: =IF(F13="","",VLOOKUP(F13,Productos!$A$2:$F$182,4,FALSE)) -> Productos de la agricultura, la silvicultura y la pesca | J13: =IF(F13="","",VLOOKUP(F13,Productos!$A$2:$F$182,5,FALSE)) -> 1 | K13: =IF(F13="","",VLOOKUP(F13,Productos!$A$2:$F$182,6,FALSE)) -> Agropecuarios | L13: 1 | M13: Bioeconomía | N13: =VLOOKUP(F13,Productos!$A$2:$J$182,5) -> 1 | O13: =VLOOKUP(F13,Productos!$A$2:$J$182,6) -> Agropecuarios
... A725: ut_f181 | B725: ATF02 | C725: Consumo intermedio | D725: P2 | E725: Consumo intermedio | F725: 181 | G725: Otros bienes y servicios | H725: =IF(F725="","",VLOOKUP(F725,Productos!$A$2:$F$182,3,FALSE)) -> 9 | I725: =IF(F725="","",VLOOKUP(F725,Productos!$A$2:$F$182,4,FALSE)) -> Servicios para la comunidad, sociales y personales | J725: =IF(F725="","",VLOOKUP(F725,Productos!$A$2:$F$182,5,FALSE)) -> 7 | K725: =IF(F725="","",VLOOKUP(F725,Productos!$A$2:$F$182,6,FALSE)) -> Otros servicios | L725: 3 | M725: No bioeconomía | N725: =VLOOKUP(F725,Productos!$A$2:$J$182,5) -> 7 | O725: =VLOOKUP(F725,Productos!$A$2:$J$182,6) -> Otros servicios
A726: va_f001 | B726: ATF06 | C726: Valor Agregado | D726: P91 | E726: Remuneraciones | H726: =IF(F726="","",VLOOKUP(F726,Productos!$A$2:$F$182,3,FALSE)) | I726: =IF(F726="","",VLOOKUP(F726,Productos!$A$2:$F$182,4,FALSE)) | J726: =IF(F726="","",VLOOKUP(F726,Productos!$A$2:$F$182,5,FALSE)) | K726: =IF(F726="","",VLOOKUP(F726,Productos!$A$2:$F$182,6,FALSE))
A727: va_f002 | H727: =IF(F727="","",VLOOKUP(F727,Productos!$A$2:$F$182,3,FALSE)) | I727: =IF(F727="","",VLOOKUP(F727,Productos!$A$2:$F$182,4,FALSE)) | J727: =IF(F727="","",VLOOKUP(F727,Productos!$A$2:$F$182,5,FALSE)) | K727: =IF(F727="","",VLOOKUP(F727,Productos!$A$2:$F$182,6,FALSE))
A728: va_f003 | H728: =IF(F728="","",VLOOKUP(F728,Productos!$A$2:$F$182,3,FALSE)) | I728: =IF(F728="","",VLOOKUP(F728,Productos!$A$2:$F$182,4,FALSE)) | J728: =IF(F728="","",VLOOKUP(F728,Productos!$A$2:$F$182,5,FALSE)) | K728: =IF(F728="","",VLOOKUP(F728,Productos!$A$2:$F$182,6,FALSE))
A729: va_f004 | B729: ATF06 | C729: Valor Agregado | D729: P92 | E729: Excedente bruto de explotación | H729: =IF(F729="","",VLOOKUP(F729,Productos!$A$2:$F$182,3,FALSE)) | I729: =IF(F729="","",VLOOKUP(F729,Productos!$A$2:$F$182,4,FALSE)) | J729: =IF(F729="","",VLOOKUP(F729,Productos!$A$2:$F$182,5,FALSE)) | K729: =IF(F729="","",VLOOKUP(F729,Productos!$A$2:$F$182,6,FALSE))
A730: va_f005 | H730: =IF(F730="","",VLOOKUP(F730,Productos!$A$2:$F$182,3,FALSE)) | I730: =IF(F730="","",VLOOKUP(F730,Productos!$A$2:$F$182,4,FALSE)) | J730: =IF(F730="","",VLOOKUP(F730,Productos!$A$2:$F$182,5,FALSE)) | K730: =IF(F730="","",VLOOKUP(F730,Productos!$A$2:$F$182,6,FALSE))
A731: va_f006 | H731: =IF(F731="","",VLOOKUP(F731,Productos!$A$2:$F$182,3,FALSE)) | I731: =IF(F731="","",VLOOKUP(F731,Productos!$A$2:$F$182,4,FALSE)) | J731: =IF(F731="","",VLOOKUP(F731,Productos!$A$2:$F$182,5,FALSE)) | K731: =IF(F731="","",VLOOKUP(F731,Productos!$A$2:$F$182,6,FALSE))
A732: va_f007 | B732: ATF06 | C732: Valor Agregado | D732: P93 | E732: Impuestos netos sobre los productos | H732: =IF(F732="","",VLOOKUP(F732,Productos!$A$2:$F$182,3,FALSE)) | I732: =IF(F732="","",VLOOKUP(F732,Productos!$A$2:$F$182,4,FALSE)) | J732: =IF(F732="","",VLOOKUP(F732,Productos!$A$2:$F$182,5,FALSE)) | K732: =IF(F732="","",VLOOKUP(F732,Productos!$A$2:$F$182,6,FALSE))
A733: va_f008 | H733: =IF(F733="","",VLOOKUP(F733,Productos!$A$2:$F$182,3,FALSE)) | I733: =IF(F733="","",VLOOKUP(F733,Productos!$A$2:$F$182,4,FALSE)) | J733: =IF(F733="","",VLOOKUP(F733,Productos!$A$2:$F$182,5,FALSE)) | K733: =IF(F733="","",VLOOKUP(F733,Productos!$A$2:$F$182,6,FALSE))
A734: va_f009 | H734: =IF(F734="","",VLOOKUP(F734,Productos!$A$2:$F$182,3,FALSE)) | I734: =IF(F734="","",VLOOKUP(F734,Productos!$A$2:$F$182,4,FALSE)) | J734: =IF(F734="","",VLOOKUP(F734,Productos!$A$2:$F$182,5,FALSE)) | K734: =IF(F734="","",VLOOKUP(F734,Productos!$A$2:$F$182,6,FALSE))
A735: va_f010 | B735: ATF06 | C735: Valor Agregado | D735: P94 | E735: Otros impuestos netos sobre la producción | H735: =IF(F735="","",VLOOKUP(F735,Productos!$A$2:$F$182,3,FALSE)) | I735: =IF(F735="","",VLOOKUP(F735,Productos!$A$2:$F$182,4,FALSE)) | J735: =IF(F735="","",VLOOKUP(F735,Productos!$A$2:$F$182,5,FALSE)) | K735: =IF(F735="","",VLOOKUP(F735,Productos!$A$2:$F$182,6,FALSE))

Sheet Columnas
A1: Columnas | B1: Código Transacciones | C1: Transacciones | D1: Código Áreas Transaccionales | E1: Áreas Transaccionales | F1: Código ATC | G1: ATC | H1: Actividades (CAE) | I1: Código CIIU Secciones | J1: CIIU Secciones | K1: CIIU Corto | L1: CIIU English | M1: Correlativo Bioeconomía Actividades | N1: Bioeconomía Actividades | O1: Código CAEc | P1: CAEc
A2: mp_c001 | B2: 1 | C2: =IF(B2="","",VLOOKUP(B2,'Transacciones CHL'!$A$2:$B$14,2,FALSE)) -> Producción bruta precio básico | D2: =IF(B2="","",VLOOKUP(B2,'Transacciones CHL'!$A$2:$F$14,3,FALSE)) -> 1 | E2: =IF(B2="","",VLOOKUP(B2,'Transacciones CHL'!$A$2:$F$14,4,FALSE)) -> Producción / Consumo intermedio | F2: =IF(B2="","",VLOOKUP(B2,'Transacciones CHL'!$A$2:$F$14,5,FALSE)) -> 1 | G2: =IF(B2="","",VLOOKUP(B2,'Transacciones CHL'!$A$2:$F$14,6,FALSE)) -> Producción / Consumo intermedio | H2: Cultivos anuales (cereales y otros) y forrajeras | I2: A | J2: Agricultura, ganadería, silvicultura y pesca | K2: Agricultura | L2: Agriculture, forestry and fishing | M2: 1 | N2: Bioeconomía | O2: 2 | P2: No culturales
A3: mp_c002 | B3: 1 | C3: =IF(B3="","",VLOOKUP(B3,'Transacciones CHL'!$A$2:$B$14,2,FALSE)) -> Producción bruta precio básico | D3: =IF(B3="","",VLOOKUP(B3,'Transacciones CHL'!$A$2:$F$14,3,FALSE)) -> 1 | E3: =IF(B3="","",VLOOKUP(B3,'Transacciones CHL'!$A$2:$F$14,4,FALSE)) -> Producción / Consumo intermedio | F3: =IF(B3="","",VLOOKUP(B3,'Transacciones CHL'!$A$2:$F$14,5,FALSE)) -> 1 | G3: =IF(B3="","",VLOOKUP(B3,'Transacciones CHL'!$A$2:$F$14,6,FALSE)) -> Producción / Consumo intermedio | H3: Cultivo de hortalizas y productos de viveros | I3: A | J3: Agricultura, ganadería, silvicultura y pesca | K3: Agricultura | L3: Agriculture, forestry and fishing | M3: 1 | N3: Bioeconomía | O3: 2 | P3: No culturales
A4: mp_c003 | B4: 1 | C4: =IF(B4="","",VLOOKUP(B4,'Transacciones CHL'!$A$2:$B$14,2,FALSE)) -> Producción bruta precio básico | D4: =IF(B4="","",VLOOKUP(B4,'Transacciones CHL'!$A$2:$F$14,3,FALSE)) -> 1 | E4: =IF(B4="","",VLOOKUP(B4,'Transacciones CHL'!$A$2:$F$14,4,FALSE)) -> Producción / Consumo intermedio | F4: =IF(B4="","",VLOOKUP(B4,'Transacciones CHL'!$A$2:$F$14,5,FALSE)) -> 1 | G4: =IF(B4="","",VLOOKUP(B4,'Transacciones CHL'!$A$2:$F$14,6,FALSE)) -> Producción / Consumo intermedio | H4: Cultivo de uva | I4: A | J4: Agricultura, ganadería, silvicultura y pesca | K4: Agricultura | L4: Agriculture, forestry and fishing | M4: 1 | N4: Bioeconomía | O4: 2 | P4: No culturales
A5: mp_c004 | B5: 1 | C5: =IF(B5="","",VLOOKUP(B5,'Transacciones CHL'!$A$2:$B$14,2,FALSE)) -> Producción bruta precio básico | D5: =IF(B5="","",VLOOKUP(B5,'Transacciones CHL'!$A$2:$F$14,3,FALSE)) -> 1 | E5: =IF(B5="","",VLOOKUP(B5,'Transacciones CHL'!$A$2:$F$14,4,FALSE)) -> Producción / Consumo intermedio | F5: =IF(B5="","",VLOOKUP(B5,'Transacciones CHL'!$A$2:$F$14,5,FALSE)) -> 1 | G5: =IF(B5="","",VLOOKUP(B5,'Transacciones CHL'!$A$2:$F$14,6,FALSE)) -> Producción / Consumo intermedio | H5: Cultivo de otras frutas | I5: A | J5: Agricultura, ganadería, silvicultura y pesca | K5: Agricultura | L5: Agriculture, forestry and fishing | M5: 1 | N5: Bioeconomía | O5: 2 | P5: No culturales
A6: mp_c005 | B6: 1 | C6: =IF(B6="","",VLOOKUP(B6,'Transacciones CHL'!$A$2:$B$14,2,FALSE)) -> Producción bruta precio básico | D6: =IF(B6="","",VLOOKUP(B6,'Transacciones CHL'!$A$2:$F$14,3,FALSE)) -> 1 | E6: =IF(B6="","",VLOOKUP(B6,'Transacciones CHL'!$A$2:$F$14,4,FALSE)) -> Producción / Consumo intermedio | F6: =IF(B6="","",VLOOKUP(B6,'Transacciones CHL'!$A$2:$F$14,5,FALSE)) -> 1 | G6: =IF(B6="","",VLOOKUP(B6,'Transacciones CHL'!$A$2:$F$14,6,FALSE)) -> Producción / Consumo intermedio | H6: Cría de ganado bovino | I6: A | J6: Agricultura, ganadería, silvicultura y pesca | K6: Agricultura | L6: Agriculture, forestry and fishing | M6: 1 | N6: Bioeconomía | O6: 2 | P6: No culturales
A7: mp_c006 | B7: 1 | C7: =IF(B7="","",VLOOKUP(B7,'Transacciones CHL'!$A$2:$B$14,2,FALSE)) -> Producción bruta precio básico | D7: =IF(B7="","",VLOOKUP(B7,'Transacciones CHL'!$A$2:$F$14,3,FALSE)) -> 1 | E7: =IF(B7="","",VLOOKUP(B7,'Transacciones CHL'!$A$2:$F$14,4,FALSE)) -> Producción / Consumo intermedio | F7: =IF(B7="","",VLOOKUP(B7,'Transacciones CHL'!$A$2:$F$14,5,FALSE)) -> 1 | G7: =IF(B7="","",VLOOKUP(B7,'Transacciones CHL'!$A$2:$F$14,6,FALSE)) -> Producción / Consumo intermedio | H7: Cría de cerdos | I7: A | J7: Agricultura, ganadería, silvicultura y pesca | K7: Agricultura | L7: Agriculture, forestry and fishing | M7: 1 | N7: Bioeconomía | O7: 2 | P7: No culturales
A8: mp_c007 | B8: 1 | C8: =IF(B8="","",VLOOKUP(B8,'Transacciones CHL'!$A$2:$B$14,2,FALSE)) -> Producción bruta precio básico | D8: =IF(B8="","",VLOOKUP(B8,'Transacciones CHL'!$A$2:$F$14,3,FALSE)) -> 1 | E8: =IF(B8="","",VLOOKUP(B8,'Transacciones CHL'!$A$2:$F$14,4,FALSE)) -> Producción / Consumo intermedio | F8: =IF(B8="","",VLOOKUP(B8,'Transacciones CHL'!$A$2:$F$14,5,FALSE)) -> 1 | G8: =IF(B8="","",VLOOKUP(B8,'Transacciones CHL'!$A$2:$F$14,6,FALSE)) -> Producción / Consumo intermedio | H8: Cría de aves de corral | I8: A | J8: Agricultura, ganadería, silvicultura y pesca | K8: Agricultura | L8: Agriculture, forestry and fishing | M8: 1 | N8: Bioeconomía | O8: 2 | P8: No culturales
A9: mp_c008 | B9: 1 | C9: =IF(B9="","",VLOOKUP(B9,'Transacciones CHL'!$A$2:$B$14,2,FALSE)) -> Producción bruta precio básico | D9: =IF(B9="","",VLOOKUP(B9,'Transacciones CHL'!$A$2:$F$14,3,FALSE)) -> 1 | E9: =IF(B9="","",VLOOKUP(B9,'Transacciones CHL'!$A$2:$F$14,4,FALSE)) -> Producción / Consumo intermedio | F9: =IF(B9="","",VLOOKUP(B9,'Transacciones CHL'!$A$2:$F$14,5,FALSE)) -> 1 | G9: =IF(B9="","",VLOOKUP(B9,'Transacciones CHL'!$A$2:$F$14,6,FALSE)) -> Producción / Consumo intermedio | H9: Cría de otros animales | I9: A | J9: Agricultura, ganadería, silvicultura y pesca | K9: Agricultura | L9: Agriculture, forestry and fishing | M9: 1 | N9: Bioeconomía | O9: 2 | P9: No culturales
A10: mp_c009 | B10: 1 | C10: =IF(B10="","",VLOOKUP(B10,'Transacciones CHL'!$A$2:$B$14,2,FALSE)) -> Producción bruta precio básico | D10: =IF(B10="","",VLOOKUP(B10,'Transacciones CHL'!$A$2:$F$14,3,FALSE)) -> 1 | E10: =IF(B10="","",VLOOKUP(B10,'Transacciones CHL'!$A$2:$F$14,4,FALSE)) -> Producción / Consumo intermedio | F10: =IF(B10="","",VLOOKUP(B10,'Transacciones CHL'!$A$2:$F$14,5,FALSE)) -> 1 | G10: =IF(B10="","",VLOOKUP(B10,'Transacciones CHL'!$A$2:$F$14,6,FALSE)) -> Producción / Consumo intermedio | H10: Actividades de apoyo a la agricultura y ganadería | I10: A | J10: Agricultura, ganadería, silvicultura y pesca | K10: Agricultura | L10: Agriculture, forestry and fishing | M10: 1 | N10: Bioeconomía | O10: 2 | P10: No culturales
A11: mp_c010 | B11: 1 | C11: =IF(B11="","",VLOOKUP(B11,'Transacciones CHL'!$A$2:$B$14,2,FALSE)) -> Producción bruta precio básico | D11: =IF(B11="","",VLOOKUP(B11,'Transacciones CHL'!$A$2:$F$14,3,FALSE)) -> 1 | E11: =IF(B11="","",VLOOKUP(B11,'Transacciones CHL'!$A$2:$F$14,4,FALSE)) -> Producción / Consumo intermedio | F11: =IF(B11="","",VLOOKUP(B11,'Transacciones CHL'!$A$2:$F$14,5,FALSE)) -> 1 | G11: =IF(B11="","",VLOOKUP(B11,'Transacciones CHL'!$A$2:$F$14,6,FALSE)) -> Producción / Consumo intermedio | H11: Silvicultura y extracción de madera | I11: A | J11: Agricultura, ganadería, silvicultura y pesca | K11: Agricultura | L11: Agriculture, forestry and fishing | M11: 1 | N11: Bioeconomía | O11: 2 | P11: No culturales
A12: mp_c011 | B12: 1 | C12: =IF(B12="","",VLOOKUP(B12,'Transacciones CHL'!$A$2:$B$14,2,FALSE)) -> Producción bruta precio básico | D12: =IF(B12="","",VLOOKUP(B12,'Transacciones CHL'!$A$2:$F$14,3,FALSE)) -> 1 | E12: =IF(B12="","",VLOOKUP(B12,'Transacciones CHL'!$A$2:$F$14,4,FALSE)) -> Producción / Consumo intermedio | F12: =IF(B12="","",VLOOKUP(B12,'Transacciones CHL'!$A$2:$F$14,5,FALSE)) -> 1 | G12: =IF(B12="","",VLOOKUP(B12,'Transacciones CHL'!$A$2:$F$14,6,FALSE)) -> Producción / Consumo intermedio | H12: Acuicultura | I12: A | J12: Agricultura, ganadería, silvicultura y pesca | K12: Agricultura | L12: Agriculture, forestry and fishing | M12: 1 | N12: Bioeconomía | O12: 2 | P12: No culturales
A13: mp_c012 | B13: 1 | C13: =IF(B13="","",VLOOKUP(B13,'Transacciones CHL'!$A$2:$B$14,2,FALSE)) -> Producción bruta precio básico | D13: =IF(B13="","",VLOOKUP(B13,'Transacciones CHL'!$A$2:$F$14,3,FALSE)) -> 1 | E13: =IF(B13="","",VLOOKUP(B13,'Transacciones CHL'!$A$2:$F$14,4,FALSE)) -> Producción / Consumo intermedio | F13: =IF(B13="","",VLOOKUP(B13,'Transacciones CHL'!$A$2:$F$14,5,FALSE)) -> 1 | G13: =IF(B13="","",VLOOKUP(B13,'Transacciones CHL'!$A$2:$F$14,6,FALSE)) -> Producción / Consumo intermedio | H13: Pesca extractiva | I13: A | J13: Agricultura, ganadería, silvicultura y pesca | K13: Agricultura | L13: Agriculture, forestry and fishing | M13: 1 | N13: Bioeconomía | O13: 2 | P13: No culturales
... A112: mp_c111 | B112: 1 | C112: =IF(B112="","",VLOOKUP(B112,'Transacciones CHL'!$A$2:$B$14,2,FALSE)) -> Producción bruta precio básico | D112: =IF(B112="","",VLOOKUP(B112,'Transacciones CHL'!$A$2:$F$14,3,FALSE)) -> 1 | E112: =IF(B112="","",VLOOKUP(B112,'Transacciones CHL'!$A$2:$F$14,4,FALSE)) -> Producción / Consumo intermedio | F112: =IF(B112="","",VLOOKUP(B112,'Transacciones CHL'!$A$2:$F$14,5,FALSE)) -> 1 | G112: =IF(B112="","",VLOOKUP(B112,'Transacciones CHL'!$A$2:$F$14,6,FALSE)) -> Producción / Consumo intermedio | H112: Otras actividades de servicios personales | I112: S | J112: Otras actividades de servicios | K112: Otros servicios | L112: Other service activities | M112: 3 | N112: No bioeconomía | O112: 2 | P112: No culturales
A113: mp_c112 | C113: =IF(B113="","",VLOOKUP(B113,'Transacciones CHL'!$A$2:$B$14,2,FALSE)) | D113: =IF(B113="","",VLOOKUP(B113,'Transacciones CHL'!$A$2:$F$14,3,FALSE)) | E113: =IF(B113="","",VLOOKUP(B113,'Transacciones CHL'!$A$2:$F$14,4,FALSE)) | F113: =IF(B113="","",VLOOKUP(B113,'Transacciones CHL'!$A$2:$F$14,5,FALSE)) | G113: =IF(B113="","",VLOOKUP(B113,'Transacciones CHL'!$A$2:$F$14,6,FALSE))
A114: ot_c001 | C114: =IF(B114="","",VLOOKUP(B114,'Transacciones CHL'!$A$2:$B$14,2,FALSE)) | D114: =IF(B114="","",VLOOKUP(B114,'Transacciones CHL'!$A$2:$F$14,3,FALSE)) | E114: =IF(B114="","",VLOOKUP(B114,'Transacciones CHL'!$A$2:$F$14,4,FALSE)) | F114: =IF(B114="","",VLOOKUP(B114,'Transacciones CHL'!$A$2:$F$14,5,FALSE)) | G114: =IF(B114="","",VLOOKUP(B114,'Transacciones CHL'!$A$2:$F$14,6,FALSE))
A115: ot_c002 | B115: 2 | C115: =IF(B115="","",VLOOKUP(B115,'Transacciones CHL'!$A$2:$B$14,2,FALSE)) -> Importaciones precios cif | D115: =IF(B115="","",VLOOKUP(B115,'Transacciones CHL'!$A$2:$F$14,3,FALSE)) -> 2 | E115: =IF(B115="","",VLOOKUP(B115,'Transacciones CHL'!$A$2:$F$14,4,FALSE)) -> Importaciones / Exportaciones | F115: =IF(B115="","",VLOOKUP(B115,'Transacciones CHL'!$A$2:$F$14,5,FALSE)) -> 2 | G115: =IF(B115="","",VLOOKUP(B115,'Transacciones CHL'!$A$2:$F$14,6,FALSE)) -> Importaciones / Exportaciones
A116: ot_c003 | C116: =IF(B116="","",VLOOKUP(B116,'Transacciones CHL'!$A$2:$B$14,2,FALSE)) | D116: =IF(B116="","",VLOOKUP(B116,'Transacciones CHL'!$A$2:$F$14,3,FALSE)) | E116: =IF(B116="","",VLOOKUP(B116,'Transacciones CHL'!$A$2:$F$14,4,FALSE)) | F116: =IF(B116="","",VLOOKUP(B116,'Transacciones CHL'!$A$2:$F$14,5,FALSE)) | G116: =IF(B116="","",VLOOKUP(B116,'Transacciones CHL'!$A$2:$F$14,6,FALSE))
A117: ot_c004 | B117: 3 | C117: =IF(B117="","",VLOOKUP(B117,'Transacciones CHL'!$A$2:$B$14,2,FALSE)) -> Impuestos indirectos sobre bienes y servicios | D117: =IF(B117="","",VLOOKUP(B117,'Transacciones CHL'!$A$2:$F$14,3,FALSE)) -> 3 | E117: =IF(B117="","",VLOOKUP(B117,'Transacciones CHL'!$A$2:$F$14,4,FALSE)) -> Impuestos indirectos sobre bienes y servicios | F117: =IF(B117="","",VLOOKUP(B117,'Transacciones CHL'!$A$2:$F$14,5,FALSE)) -> 3 | G117: =IF(B117="","",VLOOKUP(B117,'Transacciones CHL'!$A$2:$F$14,6,FALSE)) -> Impuestos
A118: ot_c005 | B118: 4 | C118: =IF(B118="","",VLOOKUP(B118,'Transacciones CHL'!$A$2:$B$14,2,FALSE)) -> Derechos de importación | D118: =IF(B118="","",VLOOKUP(B118,'Transacciones CHL'!$A$2:$F$14,3,FALSE)) -> 4 | E118: =IF(B118="","",VLOOKUP(B118,'Transacciones CHL'!$A$2:$F$14,4,FALSE)) -> Derechos de importación | F118: =IF(B118="","",VLOOKUP(B118,'Transacciones CHL'!$A$2:$F$14,5,FALSE)) -> 3 | G118: =IF(B118="","",VLOOKUP(B118,'Transacciones CHL'!$A$2:$F$14,6,FALSE)) -> Impuestos
A119: ot_c006 | C119: =IF(B119="","",VLOOKUP(B119,'Transacciones CHL'!$A$2:$B$14,2,FALSE)) | D119: =IF(B119="","",VLOOKUP(B119,'Transacciones CHL'!$A$2:$F$14,3,FALSE)) | E119: =IF(B119="","",VLOOKUP(B119,'Transacciones CHL'!$A$2:$F$14,4,FALSE)) | F119: =IF(B119="","",VLOOKUP(B119,'Transacciones CHL'!$A$2:$F$14,5,FALSE)) | G119: =IF(B119="","",VLOOKUP(B119,'Transacciones CHL'!$A$2:$F$14,6,FALSE))
A120: ot_c007 | B120: 5 | C120: =IF(B120="","",VLOOKUP(B120,'Transacciones CHL'!$A$2:$B$14,2,FALSE)) -> Margen de comercio | D120: =IF(B120="","",VLOOKUP(B120,'Transacciones CHL'!$A$2:$F$14,3,FALSE)) -> 5 | E120: =IF(B120="","",VLOOKUP(B120,'Transacciones CHL'!$A$2:$F$14,4,FALSE)) -> Margen de comercio | F120: =IF(B120="","",VLOOKUP(B120,'Transacciones CHL'!$A$2:$F$14,5,FALSE)) -> 4 | G120: =IF(B120="","",VLOOKUP(B120,'Transacciones CHL'!$A$2:$F$14,6,FALSE)) -> Márgenes
A121: ot_c008 | B121: 6 | C121: =IF(B121="","",VLOOKUP(B121,'Transacciones CHL'!$A$2:$B$14,2,FALSE)) -> Impuesto al valor agregado | D121: =IF(B121="","",VLOOKUP(B121,'Transacciones CHL'!$A$2:$F$14,3,FALSE)) -> 6 | E121: =IF(B121="","",VLOOKUP(B121,'Transacciones CHL'!$A$2:$F$14,4,FALSE)) -> Impuesto al valor agregado | F121: =IF(B121="","",VLOOKUP(B121,'Transacciones CHL'!$A$2:$F$14,5,FALSE)) -> 3 | G121: =IF(B121="","",VLOOKUP(B121,'Transacciones CHL'!$A$2:$F$14,6,FALSE)) -> Impuestos
A122: ot_c009 | C122: =IF(B122="","",VLOOKUP(B122,'Transacciones CHL'!$A$2:$B$14,2,FALSE)) | D122: =IF(B122="","",VLOOKUP(B122,'Transacciones CHL'!$A$2:$F$14,3,FALSE)) | E122: =IF(B122="","",VLOOKUP(B122,'Transacciones CHL'!$A$2:$F$14,4,FALSE)) | F122: =IF(B122="","",VLOOKUP(B122,'Transacciones CHL'!$A$2:$F$14,5,FALSE)) | G122: =IF(B122="","",VLOOKUP(B122,'Transacciones CHL'!$A$2:$F$14,6,FALSE))
A123: ui_c001 | B123: 7 | C123: =IF(B123="","",VLOOKUP(B123,'Transacciones CHL'!$A$2:$B$14,2,FALSE)) -> Consumo intermedio | D123: =IF(B123="","",VLOOKUP(B123,'Transacciones CHL'!$A$2:$F$14,3,FALSE)) -> 1 | E123: =IF(B123="","",VLOOKUP(B123,'Transacciones CHL'!$A$2:$F$14,4,FALSE)) -> Producción / Consumo intermedio | F123: =IF(B123="","",VLOOKUP(B123,'Transacciones CHL'!$A$2:$F$14,5,FALSE)) -> 1 | G123: =IF(B123="","",VLOOKUP(B123,'Transacciones CHL'!$A$2:$F$14,6,FALSE)) -> Producción / Consumo intermedio | H123: Cultivos anuales (cereales y otros) y forrajeras | I123: A | J123: Agricultura, ganadería, silvicultura y pesca | K123: Agricultura | L123: Agriculture, forestry and fishing | M123: 1 | N123: Bioeconomía | O123: 2 | P123: No culturales
A124: ui_c002 | B124: 7 | C124: =IF(B124="","",VLOOKUP(B124,'Transacciones CHL'!$A$2:$B$14,2,FALSE)) -> Consumo intermedio | D124: =IF(B124="","",VLOOKUP(B124,'Transacciones CHL'!$A$2:$F$14,3,FALSE)) -> 1 | E124: =IF(B124="","",VLOOKUP(B124,'Transacciones CHL'!$A$2:$F$14,4,FALSE)) -> Producción / Consumo intermedio | F124: =IF(B124="","",VLOOKUP(B124,'Transacciones CHL'!$A$2:$F$14,5,FALSE)) -> 1 | G124: =IF(B124="","",VLOOKUP(B124,'Transacciones CHL'!$A$2:$F$14,6,FALSE)) -> Producción / Consumo intermedio | H124: Cultivo de hortalizas y productos de viveros | I124: A | J124: Agricultura, ganadería, silvicultura y pesca | K124: Agricultura | L124: Agriculture, forestry and fishing | M124: 1 | N124: Bioeconomía | O124: 2 | P124: No culturales
A125: ui_c003 | B125: 7 | C125: =IF(B125="","",VLOOKUP(B125,'Transacciones CHL'!$A$2:$B$14,2,FALSE)) -> Consumo intermedio | D125: =IF(B125="","",VLOOKUP(B125,'Transacciones CHL'!$A$2:$F$14,3,FALSE)) -> 1 | E125: =IF(B125="","",VLOOKUP(B125,'Transacciones CHL'!$A$2:$F$14,4,FALSE)) -> Producción / Consumo intermedio | F125: =IF(B125="","",VLOOKUP(B125,'Transacciones CHL'!$A$2:$F$14,5,FALSE)) -> 1 | G125: =IF(B125="","",VLOOKUP(B125,'Transacciones CHL'!$A$2:$F$14,6,FALSE)) -> Producción / Consumo intermedio | H125: Cultivo de uva | I125: A | J125: Agricultura, ganadería, silvicultura y pesca | K125: Agricultura | L125: Agriculture, forestry and fishing | M125: 1 | N125: Bioeconomía | O125: 2 | P125: No culturales
A126: ui_c004 | B126: 7 | C126: =IF(B126="","",VLOOKUP(B126,'Transacciones CHL'!$A$2:$B$14,2,FALSE)) -> Consumo intermedio | D126: =IF(B126="","",VLOOKUP(B126,'Transacciones CHL'!$A$2:$F$14,3,FALSE)) -> 1 | E126: =IF(B126="","",VLOOKUP(B126,'Transacciones CHL'!$A$2:$F$14,4,FALSE)) -> Producción / Consumo intermedio | F126: =IF(B126="","",VLOOKUP(B126,'Transacciones CHL'!$A$2:$F$14,5,FALSE)) -> 1 | G126: =IF(B126="","",VLOOKUP(B126,'Transacciones CHL'!$A$2:$F$14,6,FALSE)) -> Producción / Consumo intermedio | H126: Cultivo de otras frutas | I126: A | J126: Agricultura, ganadería, silvicultura y pesca | K126: Agricultura | L126: Agriculture, forestry and fishing | M126: 1 | N126: Bioeconomía | O126: 2 | P126: No culturales
A127: ui_c005 | B127: 7 | C127: =IF(B127="","",VLOOKUP(B127,'Transacciones CHL'!$A$2:$B$14,2,FALSE)) -> Consumo intermedio | D127: =IF(B127="","",VLOOKUP(B127,'Transacciones CHL'!$A$2:$F$14,3,FALSE)) -> 1 | E127: =IF(B127="","",VLOOKUP(B127,'Transacciones CHL'!$A$2:$F$14,4,FALSE)) -> Producción / Consumo intermedio | F127: =IF(B127="","",VLOOKUP(B127,'Transacciones CHL'!$A$2:$F$14,5,FALSE)) -> 1 | G127: =IF(B127="","",VLOOKUP(B127,'Transacciones CHL'!$A$2:$F$14,6,FALSE)) -> Producción / Consumo intermedio | H127: Cría de ganado bovino | I127: A | J127: Agricultura, ganadería, silvicultura y pesca | K127: Agricultura | L127: Agriculture, forestry and fishing | M127: 1 | N127: Bioeconomía | O127: 2 | P127: No culturales
A128: ui_c006 | B128: 7 | C128: =IF(B128="","",VLOOKUP(B128,'Transacciones CHL'!$A$2:$B$14,2,FALSE)) -> Consumo intermedio | D128: =IF(B128="","",VLOOKUP(B128,'Transacciones CHL'!$A$2:$F$14,3,FALSE)) -> 1 | E128: =IF(B128="","",VLOOKUP(B128,'Transacciones CHL'!$A$2:$F$14,4,FALSE)) -> Producción / Consumo intermedio | F128: =IF(B128="","",VLOOKUP(B128,'Transacciones CHL'!$A$2:$F$14,5,FALSE)) -> 1 | G128: =IF(B128="","",VLOOKUP(B128,'Transacciones CHL'!$A$2:$F$14,6,FALSE)) -> Producción / Consumo intermedio | H128: Cría de cerdos | I128: A | J128: Agricultura, ganadería, silvicultura y pesca | K128: Agricultura | L128: Agriculture, forestry and fishing | M128: 1 | N128: Bioeconomía | O128: 2 | P128: No culturales
A129: ui_c007 | B129: 7 | C129: =IF(B129="","",VLOOKUP(B129,'Transacciones CHL'!$A$2:$B$14,2,FALSE)) -> Consumo intermedio | D129: =IF(B129="","",VLOOKUP(B129,'Transacciones CHL'!$A$2:$F$14,3,FALSE)) -> 1 | E129: =IF(B129="","",VLOOKUP(B129,'Transacciones CHL'!$A$2:$F$14,4,FALSE)) -> Producción / Consumo intermedio | F129: =IF(B129="","",VLOOKUP(B129,'Transacciones CHL'!$A$2:$F$14,5,FALSE)) -> 1 | G129: =IF(B129="","",VLOOKUP(B129,'Transacciones CHL'!$A$2:$F$14,6,FALSE)) -> Producción / Consumo intermedio | H129: Cría de aves de corral | I129: A | J129: Agricultura, ganadería, silvicultura y pesca | K129: Agricultura | L129: Agriculture, forestry and fishing | M129: 1 | N129: Bioeconomía | O129: 2 | P129: No culturales
A130: ui_c008 | B130: 7 | C130: =IF(B130="","",VLOOKUP(B130,'Transacciones CHL'!$A$2:$B$14,2,FALSE)) -> Consumo intermedio | D130: =IF(B130="","",VLOOKUP(B130,'Transacciones CHL'!$A$2:$F$14,3,FALSE)) -> 1 | E130: =IF(B130="","",VLOOKUP(B130,'Transacciones CHL'!$A$2:$F$14,4,FALSE)) -> Producción / Consumo intermedio | F130: =IF(B130="","",VLOOKUP(B130,'Transacciones CHL'!$A$2:$F$14,5,FALSE)) -> 1 | G130: =IF(B130="","",VLOOKUP(B130,'Transacciones CHL'!$A$2:$F$14,6,FALSE)) -> Producción / Consumo intermedio | H130: Cría de otros animales | I130: A | J130: Agricultura, ganadería, silvicultura y pesca | K130: Agricultura | L130: Agriculture, forestry and fishing | M130: 1 | N130: Bioeconomía | O130: 2 | P130: No culturales
A131: ui_c009 | B131: 7 | C131: =IF(B131="","",VLOOKUP(B131,'Transacciones CHL'!$A$2:$B$14,2,FALSE)) -> Consumo intermedio | D131: =IF(B131="","",VLOOKUP(B131,'Transacciones CHL'!$A$2:$F$14,3,FALSE)) -> 1 | E131: =IF(B131="","",VLOOKUP(B131,'Transacciones CHL'!$A$2:$F$14,4,FALSE)) -> Producción / Consumo intermedio | F131: =IF(B131="","",VLOOKUP(B131,'Transacciones CHL'!$A$2:$F$14,5,FALSE)) -> 1 | G131: =IF(B131="","",VLOOKUP(B131,'Transacciones CHL'!$A$2:$F$14,6,FALSE)) -> Producción / Consumo intermedio | H131: Actividades de apoyo a la agricultura y ganadería | I131: A | J131: Agricultura, ganadería, silvicultura y pesca | K131: Agricultura | L131: Agriculture, forestry and fishing | M131: 1 | N131: Bioeconomía | O131: 2 | P131: No culturales
A132: ui_c010 | B132: 7 | C132: =IF(B132="","",VLOOKUP(B132,'Transacciones CHL'!$A$2:$B$14,2,FALSE)) -> Consumo intermedio | D132: =IF(B132="","",VLOOKUP(B132,'Transacciones CHL'!$A$2:$F$14,3,FALSE)) -> 1 | E132: =IF(B132="","",VLOOKUP(B132,'Transacciones CHL'!$A$2:$F$14,4,FALSE)) -> Producción / Consumo intermedio | F132: =IF(B132="","",VLOOKUP(B132,'Transacciones CHL'!$A$2:$F$14,5,FALSE)) -> 1 | G132: =IF(B132="","",VLOOKUP(B132,'Transacciones CHL'!$A$2:$F$14,6,FALSE)) -> Producción / Consumo intermedio | H132: Silvicultura y extracción de madera | I132: A | J132: Agricultura, ganadería, silvicultura y pesca | K132: Agricultura | L132: Agriculture, forestry and fishing | M132: 1 | N132: Bioeconomía | O132: 2 | P132: No culturales
A133: ui_c011 | B133: 7 | C133: =IF(B133="","",VLOOKUP(B133,'Transacciones CHL'!$A$2:$B$14,2,FALSE)) -> Consumo intermedio | D133: =IF(B133="","",VLOOKUP(B133,'Transacciones CHL'!$A$2:$F$14,3,FALSE)) -> 1 | E133: =IF(B133="","",VLOOKUP(B133,'Transacciones CHL'!$A$2:$F$14,4,FALSE)) -> Producción / Consumo intermedio | F133: =IF(B133="","",VLOOKUP(B133,'Transacciones CHL'!$A$2:$F$14,5,FALSE)) -> 1 | G133: =IF(B133="","",VLOOKUP(B133,'Transacciones CHL'!$A$2:$F$14,6,FALSE)) -> Producción / Consumo intermedio | H133: Acuicultura | I133: A | J133: Agricultura, ganadería, silvicultura y pesca | K133: Agricultura | L133: Agriculture, forestry and fishing | M133: 1 | N133: Bioeconomía | O133: 2 | P133: No culturales
A134: ui_c012 | B134: 7 | C134: =IF(B134="","",VLOOKUP(B134,'Transacciones CHL'!$A$2:$B$14,2,FALSE)) -> Consumo intermedio | D134: =IF(B134="","",VLOOKUP(B134,'Transacciones CHL'!$A$2:$F$14,3,FALSE)) -> 1 | E134: =IF(B134="","",VLOOKUP(B134,'Transacciones CHL'!$A$2:$F$14,4,FALSE)) -> Producción / Consumo intermedio | F134: =IF(B134="","",VLOOKUP(B134,'Transacciones CHL'!$A$2:$F$14,5,FALSE)) -> 1 | G134: =IF(B134="","",VLOOKUP(B134,'Transacciones CHL'!$A$2:$F$14,6,FALSE)) -> Producción / Consumo intermedio | H134: Pesca extractiva | I134: A | J134: Agricultura, ganadería, silvicultura y pesca | K134: Agricultura | L134: Agriculture, forestry and fishing | M134: 1 | N134: Bioeconomía | O134: 2 | P134: No culturales
... A233: ui_c111 | B233: 7 | C233: =IF(B233="","",VLOOKUP(B233,'Transacciones CHL'!$A$2:$B$14,2,FALSE)) -> Consumo intermedio | D233: =IF(B233="","",VLOOKUP(B233,'Transacciones CHL'!$A$2:$F$14,3,FALSE)) -> 1 | E233: =IF(B233="","",VLOOKUP(B233,'Transacciones CHL'!$A$2:$F$14,4,FALSE)) -> Producción / Consumo intermedio | F233: =IF(B233="","",VLOOKUP(B233,'Transacciones CHL'!$A$2:$F$14,5,FALSE)) -> 1 | G233: =IF(B233="","",VLOOKUP(B233,'Transacciones CHL'!$A$2:$F$14,6,FALSE)) -> Producción / Consumo intermedio | H233: Otras actividades de servicios personales | I233: S | J233: Otras actividades de servicios | K233: Otros servicios | L233: Other service activities | M233: 3 | N233: No bioeconomía | O233: 2 | P233: No culturales
A234: ui_c112 | C234: =IF(B234="","",VLOOKUP(B234,'Transacciones CHL'!$A$2:$B$14,2,FALSE)) | D234: =IF(B234="","",VLOOKUP(B234,'Transacciones CHL'!$A$2:$F$14,3,FALSE)) | E234: =IF(B234="","",VLOOKUP(B234,'Transacciones CHL'!$A$2:$F$14,4,FALSE)) | F234: =IF(B234="","",VLOOKUP(B234,'Transacciones CHL'!$A$2:$F$14,5,FALSE)) | G234: =IF(B234="","",VLOOKUP(B234,'Transacciones CHL'!$A$2:$F$14,6,FALSE))
A235: ut_c001 | C235: =IF(B235="","",VLOOKUP(B235,'Transacciones CHL'!$A$2:$B$14,2,FALSE)) | D235: =IF(B235="","",VLOOKUP(B235,'Transacciones CHL'!$A$2:$F$14,3,FALSE)) | E235: =IF(B235="","",VLOOKUP(B235,'Transacciones CHL'!$A$2:$F$14,4,FALSE)) | F235: =IF(B235="","",VLOOKUP(B235,'Transacciones CHL'!$A$2:$F$14,5,FALSE)) | G235: =IF(B235="","",VLOOKUP(B235,'Transacciones CHL'!$A$2:$F$14,6,FALSE))
A236: ut_c002 | B236: 8 | C236: =IF(B236="","",VLOOKUP(B236,'Transacciones CHL'!$A$2:$B$14,2,FALSE)) -> Consumo de hogares | D236: =IF(B236="","",VLOOKUP(B236,'Transacciones CHL'!$A$2:$F$14,3,FALSE)) -> 7 | E236: =IF(B236="","",VLOOKUP(B236,'Transacciones CHL'!$A$2:$F$14,4,FALSE)) -> Consumo de hogares | F236: =IF(B236="","",VLOOKUP(B236,'Transacciones CHL'!$A$2:$F$14,5,FALSE)) -> 5 | G236: =IF(B236="","",VLOOKUP(B236,'Transacciones CHL'!$A$2:$F$14,6,FALSE)) -> Consumo final
A237: ut_c003 | B237: 9 | C237: =IF(B237="","",VLOOKUP(B237,'Transacciones CHL'!$A$2:$B$14,2,FALSE)) -> Consumo de IPSFL | D237: =IF(B237="","",VLOOKUP(B237,'Transacciones CHL'!$A$2:$F$14,3,FALSE)) -> 8 | E237: =IF(B237="","",VLOOKUP(B237,'Transacciones CHL'!$A$2:$F$14,4,FALSE)) -> Consumo de IPSFL | F237: =IF(B237="","",VLOOKUP(B237,'Transacciones CHL'!$A$2:$F$14,5,FALSE)) -> 5 | G237: =IF(B237="","",VLOOKUP(B237,'Transacciones CHL'!$A$2:$F$14,6,FALSE)) -> Consumo final
A238: ut_c004 | B238: 10 | C238: =IF(B238="","",VLOOKUP(B238,'Transacciones CHL'!$A$2:$B$14,2,FALSE)) -> Consumo de gobierno | D238: =IF(B238="","",VLOOKUP(B238,'Transacciones CHL'!$A$2:$F$14,3,FALSE)) -> 9 | E238: =IF(B238="","",VLOOKUP(B238,'Transacciones CHL'!$A$2:$F$14,4,FALSE)) -> Consumo de gobierno | F238: =IF(B238="","",VLOOKUP(B238,'Transacciones CHL'!$A$2:$F$14,5,FALSE)) -> 5 | G238: =IF(B238="","",VLOOKUP(B238,'Transacciones CHL'!$A$2:$F$14,6,FALSE)) -> Consumo final
A239: ut_c005 | B239: 11 | C239: =IF(B239="","",VLOOKUP(B239,'Transacciones CHL'!$A$2:$B$14,2,FALSE)) -> Formación bruta de capital fijo | D239: =IF(B239="","",VLOOKUP(B239,'Transacciones CHL'!$A$2:$F$14,3,FALSE)) -> 10 | E239: =IF(B239="","",VLOOKUP(B239,'Transacciones CHL'!$A$2:$F$14,4,FALSE)) -> Formación bruta de capital fijo | F239: =IF(B239="","",VLOOKUP(B239,'Transacciones CHL'!$A$2:$F$14,5,FALSE)) -> 6 | G239: =IF(B239="","",VLOOKUP(B239,'Transacciones CHL'!$A$2:$F$14,6,FALSE)) -> FBK / Variación existencias
A240: ut_c006 | B240: 12 | C240: =IF(B240="","",VLOOKUP(B240,'Transacciones CHL'!$A$2:$B$14,2,FALSE)) -> Variación de existencias | D240: =IF(B240="","",VLOOKUP(B240,'Transacciones CHL'!$A$2:$F$14,3,FALSE)) -> 11 | E240: =IF(B240="","",VLOOKUP(B240,'Transacciones CHL'!$A$2:$F$14,4,FALSE)) -> Variación de existencias | F240: =IF(B240="","",VLOOKUP(B240,'Transacciones CHL'!$A$2:$F$14,5,FALSE)) -> 6 | G240: =IF(B240="","",VLOOKUP(B240,'Transacciones CHL'!$A$2:$F$14,6,FALSE)) -> FBK / Variación existencias
A241: ut_c007 | B241: 13 | C241: =IF(B241="","",VLOOKUP(B241,'Transacciones CHL'!$A$2:$B$14,2,FALSE)) -> Exportaciones | D241: =IF(B241="","",VLOOKUP(B241,'Transacciones CHL'!$A$2:$F$14,3,FALSE)) -> 2 | E241: =IF(B241="","",VLOOKUP(B241,'Transacciones CHL'!$A$2:$F$14,4,FALSE)) -> Importaciones / Exportaciones | F241: =IF(B241="","",VLOOKUP(B241,'Transacciones CHL'!$A$2:$F$14,5,FALSE)) -> 2 | G241: =IF(B241="","",VLOOKUP(B241,'Transacciones CHL'!$A$2:$F$14,6,FALSE)) -> Importaciones / Exportaciones
A242: ut_c008 | C242: =IF(B242="","",VLOOKUP(B242,'Transacciones CHL'!$A$2:$B$14,2,FALSE)) | D242: =IF(B242="","",VLOOKUP(B242,'Transacciones CHL'!$A$2:$F$14,3,FALSE)) | E242: =IF(B242="","",VLOOKUP(B242,'Transacciones CHL'!$A$2:$F$14,4,FALSE)) | F242: =IF(B242="","",VLOOKUP(B242,'Transacciones CHL'!$A$2:$F$14,5,FALSE)) | G242: =IF(B242="","",VLOOKUP(B242,'Transacciones CHL'!$A$2:$F$14,6,FALSE))
A243: ut_c009 | C243: =IF(B243="","",VLOOKUP(B243,'Transacciones CHL'!$A$2:$B$14,2,FALSE)) | D243: =IF(B243="","",VLOOKUP(B243,'Transacciones CHL'!$A$2:$F$14,3,FALSE)) | E243: =IF(B243="","",VLOOKUP(B243,'Transacciones CHL'!$A$2:$F$14,4,FALSE)) | F243: =IF(B243="","",VLOOKUP(B243,'Transacciones CHL'!$A$2:$F$14,5,FALSE)) | G243: =IF(B243="","",VLOOKUP(B243,'Transacciones CHL'!$A$2:$F$14,6,FALSE))
A244: va_c001 | B244: 1 | C244: =IF(B244="","",VLOOKUP(B244,'Transacciones CHL'!$A$2:$B$14,2,FALSE)) -> Producción bruta precio básico | D244: =IF(B244="","",VLOOKUP(B244,'Transacciones CHL'!$A$2:$F$14,3,FALSE)) -> 1 | E244: =IF(B244="","",VLOOKUP(B244,'Transacciones CHL'!$A$2:$F$14,4,FALSE)) -> Producción / Consumo intermedio | F244: =IF(B244="","",VLOOKUP(B244,'Transacciones CHL'!$A$2:$F$14,5,FALSE)) -> 1 | G244: =IF(B244="","",VLOOKUP(B244,'Transacciones CHL'!$A$2:$F$14,6,FALSE)) -> Producción / Consumo intermedio | H244: Cultivos anuales (cereales y otros) y forrajeras | I244: A | J244: Agricultura, ganadería, silvicultura y pesca | K244: Agricultura | L244: Agriculture, forestry and fishing | M244: 1 | N244: Bioeconomía | O244: 2 | P244: No culturales
A245: va_c002 | B245: 1 | C245: =IF(B245="","",VLOOKUP(B245,'Transacciones CHL'!$A$2:$B$14,2,FALSE)) -> Producción bruta precio básico | D245: =IF(B245="","",VLOOKUP(B245,'Transacciones CHL'!$A$2:$F$14,3,FALSE)) -> 1 | E245: =IF(B245="","",VLOOKUP(B245,'Transacciones CHL'!$A$2:$F$14,4,FALSE)) -> Producción / Consumo intermedio | F245: =IF(B245="","",VLOOKUP(B245,'Transacciones CHL'!$A$2:$F$14,5,FALSE)) -> 1 | G245: =IF(B245="","",VLOOKUP(B245,'Transacciones CHL'!$A$2:$F$14,6,FALSE)) -> Producción / Consumo intermedio | H245: Cultivo de hortalizas y productos de viveros | I245: A | J245: Agricultura, ganadería, silvicultura y pesca | K245: Agricultura | L245: Agriculture, forestry and fishing | M245: 1 | N245: Bioeconomía | O245: 2 | P245: No culturales
A246: va_c003 | B246: 1 | C246: =IF(B246="","",VLOOKUP(B246,'Transacciones CHL'!$A$2:$B$14,2,FALSE)) -> Producción bruta precio básico | D246: =IF(B246="","",VLOOKUP(B246,'Transacciones CHL'!$A$2:$F$14,3,FALSE)) -> 1 | E246: =IF(B246="","",VLOOKUP(B246,'Transacciones CHL'!$A$2:$F$14,4,FALSE)) -> Producción / Consumo intermedio | F246: =IF(B246="","",VLOOKUP(B246,'Transacciones CHL'!$A$2:$F$14,5,FALSE)) -> 1 | G246: =IF(B246="","",VLOOKUP(B246,'Transacciones CHL'!$A$2:$F$14,6,FALSE)) -> Producción / Consumo intermedio | H246: Cultivo de uva | I246: A | J246: Agricultura, ganadería, silvicultura y pesca | K246: Agricultura | L246: Agriculture, forestry and fishing | M246: 1 | N246: Bioeconomía | O246: 2 | P246: No culturales
A247: va_c004 | B247: 1 | C247: =IF(B247="","",VLOOKUP(B247,'Transacciones CHL'!$A$2:$B$14,2,FALSE)) -> Producción bruta precio básico | D247: =IF(B247="","",VLOOKUP(B247,'Transacciones CHL'!$A$2:$F$14,3,FALSE)) -> 1 | E247: =IF(B247="","",VLOOKUP(B247,'Transacciones CHL'!$A$2:$F$14,4,FALSE)) -> Producción / Consumo intermedio | F247: =IF(B247="","",VLOOKUP(B247,'Transacciones CHL'!$A$2:$F$14,5,FALSE)) -> 1 | G247: =IF(B247="","",VLOOKUP(B247,'Transacciones CHL'!$A$2:$F$14,6,FALSE)) -> Producción / Consumo intermedio | H247: Cultivo de otras frutas | I247: A | J247: Agricultura, ganadería, silvicultura y pesca | K247: Agricultura | L247: Agriculture, forestry and fishing | M247: 1 | N247: Bioeconomía | O247: 2 | P247: No culturales
A248: va_c005 | B248: 1 | C248: =IF(B248="","",VLOOKUP(B248,'Transacciones CHL'!$A$2:$B$14,2,FALSE)) -> Producción bruta precio básico | D248: =IF(B248="","",VLOOKUP(B248,'Transacciones CHL'!$A$2:$F$14,3,FALSE)) -> 1 | E248: =IF(B248="","",VLOOKUP(B248,'Transacciones CHL'!$A$2:$F$14,4,FALSE)) -> Producción / Consumo intermedio | F248: =IF(B248="","",VLOOKUP(B248,'Transacciones CHL'!$A$2:$F$14,5,FALSE)) -> 1 | G248: =IF(B248="","",VLOOKUP(B248,'Transacciones CHL'!$A$2:$F$14,6,FALSE)) -> Producción / Consumo intermedio | H248: Cría de ganado bovino | I248: A | J248: Agricultura, ganadería, silvicultura y pesca | K248: Agricultura | L248: Agriculture, forestry and fishing | M248: 1 | N248: Bioeconomía | O248: 2 | P248: No culturales
A249: va_c006 | B249: 1 | C249: =IF(B249="","",VLOOKUP(B249,'Transacciones CHL'!$A$2:$B$14,2,FALSE)) -> Producción bruta precio básico | D249: =IF(B249="","",VLOOKUP(B249,'Transacciones CHL'!$A$2:$F$14,3,FALSE)) -> 1 | E249: =IF(B249="","",VLOOKUP(B249,'Transacciones CHL'!$A$2:$F$14,4,FALSE)) -> Producción / Consumo intermedio | F249: =IF(B249="","",VLOOKUP(B249,'Transacciones CHL'!$A$2:$F$14,5,FALSE)) -> 1 | G249: =IF(B249="","",VLOOKUP(B249,'Transacciones CHL'!$A$2:$F$14,6,FALSE)) -> Producción / Consumo intermedio | H249: Cría de cerdos | I249: A | J249: Agricultura, ganadería, silvicultura y pesca | K249: Agricultura | L249: Agriculture, forestry and fishing | M249: 1 | N249: Bioeconomía | O249: 2 | P249: No culturales
A250: va_c007 | B250: 1 | C250: =IF(B250="","",VLOOKUP(B250,'Transacciones CHL'!$A$2:$B$14,2,FALSE)) -> Producción bruta precio básico | D250: =IF(B250="","",VLOOKUP(B250,'Transacciones CHL'!$A$2:$F$14,3,FALSE)) -> 1 | E250: =IF(B250="","",VLOOKUP(B250,'Transacciones CHL'!$A$2:$F$14,4,FALSE)) -> Producción / Consumo intermedio | F250: =IF(B250="","",VLOOKUP(B250,'Transacciones CHL'!$A$2:$F$14,5,FALSE)) -> 1 | G250: =IF(B250="","",VLOOKUP(B250,'Transacciones CHL'!$A$2:$F$14,6,FALSE)) -> Producción / Consumo intermedio | H250: Cría de aves de corral | I250: A | J250: Agricultura, ganadería, silvicultura y pesca | K250: Agricultura | L250: Agriculture, forestry and fishing | M250: 1 | N250: Bioeconomía | O250: 2 | P250: No culturales
A251: va_c008 | B251: 1 | C251: =IF(B251="","",VLOOKUP(B251,'Transacciones CHL'!$A$2:$B$14,2,FALSE)) -> Producción bruta precio básico | D251: =IF(B251="","",VLOOKUP(B251,'Transacciones CHL'!$A$2:$F$14,3,FALSE)) -> 1 | E251: =IF(B251="","",VLOOKUP(B251,'Transacciones CHL'!$A$2:$F$14,4,FALSE)) -> Producción / Consumo intermedio | F251: =IF(B251="","",VLOOKUP(B251,'Transacciones CHL'!$A$2:$F$14,5,FALSE)) -> 1 | G251: =IF(B251="","",VLOOKUP(B251,'Transacciones CHL'!$A$2:$F$14,6,FALSE)) -> Producción / Consumo intermedio | H251: Cría de otros animales | I251: A | J251: Agricultura, ganadería, silvicultura y pesca | K251: Agricultura | L251: Agriculture, forestry and fishing | M251: 1 | N251: Bioeconomía | O251: 2 | P251: No culturales
A252: va_c009 | B252: 1 | C252: =IF(B252="","",VLOOKUP(B252,'Transacciones CHL'!$A$2:$B$14,2,FALSE)) -> Producción bruta precio básico | D252: =IF(B252="","",VLOOKUP(B252,'Transacciones CHL'!$A$2:$F$14,3,FALSE)) -> 1 | E252: =IF(B252="","",VLOOKUP(B252,'Transacciones CHL'!$A$2:$F$14,4,FALSE)) -> Producción / Consumo intermedio | F252: =IF(B252="","",VLOOKUP(B252,'Transacciones CHL'!$A$2:$F$14,5,FALSE)) -> 1 | G252: =IF(B252="","",VLOOKUP(B252,'Transacciones CHL'!$A$2:$F$14,6,FALSE)) -> Producción / Consumo intermedio | H252: Actividades de apoyo a la agricultura y ganadería | I252: A | J252: Agricultura, ganadería, silvicultura y pesca | K252: Agricultura | L252: Agriculture, forestry and fishing | M252: 1 | N252: Bioeconomía | O252: 2 | P252: No culturales
A253: va_c010 | B253: 1 | C253: =IF(B253="","",VLOOKUP(B253,'Transacciones CHL'!$A$2:$B$14,2,FALSE)) -> Producción bruta precio básico | D253: =IF(B253="","",VLOOKUP(B253,'Transacciones CHL'!$A$2:$F$14,3,FALSE)) -> 1 | E253: =IF(B253="","",VLOOKUP(B253,'Transacciones CHL'!$A$2:$F$14,4,FALSE)) -> Producción / Consumo intermedio | F253: =IF(B253="","",VLOOKUP(B253,'Transacciones CHL'!$A$2:$F$14,5,FALSE)) -> 1 | G253: =IF(B253="","",VLOOKUP(B253,'Transacciones CHL'!$A$2:$F$14,6,FALSE)) -> Producción / Consumo intermedio | H253: Silvicultura y extracción de madera | I253: A | J253: Agricultura, ganadería, silvicultura y pesca | K253: Agricultura | L253: Agriculture, forestry and fishing | M253: 1 | N253: Bioeconomía | O253: 2 | P253: No culturales
A254: va_c011 | B254: 1 | C254: =IF(B254="","",VLOOKUP(B254,'Transacciones CHL'!$A$2:$B$14,2,FALSE)) -> Producción bruta precio básico | D254: =IF(B254="","",VLOOKUP(B254,'Transacciones CHL'!$A$2:$F$14,3,FALSE)) -> 1 | E254: =IF(B254="","",VLOOKUP(B254,'Transacciones CHL'!$A$2:$F$14,4,FALSE)) -> Producción / Consumo intermedio | F254: =IF(B254="","",VLOOKUP(B254,'Transacciones CHL'!$A$2:$F$14,5,FALSE)) -> 1 | G254: =IF(B254="","",VLOOKUP(B254,'Transacciones CHL'!$A$2:$F$14,6,FALSE)) -> Producción / Consumo intermedio | H254: Acuicultura | I254: A | J254: Agricultura, ganadería, silvicultura y pesca | K254: Agricultura | L254: Agriculture, forestry and fishing | M254: 1 | N254: Bioeconomía | O254: 2 | P254: No culturales
A255: va_c012 | B255: 1 | C255: =IF(B255="","",VLOOKUP(B255,'Transacciones CHL'!$A$2:$B$14,2,FALSE)) -> Producción bruta precio básico | D255: =IF(B255="","",VLOOKUP(B255,'Transacciones CHL'!$A$2:$F$14,3,FALSE)) -> 1 | E255: =IF(B255="","",VLOOKUP(B255,'Transacciones CHL'!$A$2:$F$14,4,FALSE)) -> Producción / Consumo intermedio | F255: =IF(B255="","",VLOOKUP(B255,'Transacciones CHL'!$A$2:$F$14,5,FALSE)) -> 1 | G255: =IF(B255="","",VLOOKUP(B255,'Transacciones CHL'!$A$2:$F$14,6,FALSE)) -> Producción / Consumo intermedio | H255: Pesca extractiva | I255: A | J255: Agricultura, ganadería, silvicultura y pesca | K255: Agricultura | L255: Agriculture, forestry and fishing | M255: 1 | N255: Bioeconomía | O255: 2 | P255: No culturales
... A354: va_c111 | B354: 1 | C354: =IF(B354="","",VLOOKUP(B354,'Transacciones CHL'!$A$2:$B$14,2,FALSE)) -> Producción bruta precio básico | D354: =IF(B354="","",VLOOKUP(B354,'Transacciones CHL'!$A$2:$F$14,3,FALSE)) -> 1 | E354: =IF(B354="","",VLOOKUP(B354,'Transacciones CHL'!$A$2:$F$14,4,FALSE)) -> Producción / Consumo intermedio | F354: =IF(B354="","",VLOOKUP(B354,'Transacciones CHL'!$A$2:$F$14,5,FALSE)) -> 1 | G354: =IF(B354="","",VLOOKUP(B354,'Transacciones CHL'!$A$2:$F$14,6,FALSE)) -> Producción / Consumo intermedio | H354: Otras actividades de servicios personales | I354: S | J354: Otras actividades de servicios | K354: Otros servicios | L354: Other service activities | M354: 3 | N354: No bioeconomía | O354: 2 | P354: No culturales
A355: va_c112 | C355: =IF(B355="","",VLOOKUP(B355,'Transacciones CHL'!$A$2:$B$14,2,FALSE)) | D355: =IF(B355="","",VLOOKUP(B355,'Transacciones CHL'!$A$2:$F$14,3,FALSE)) | E355: =IF(B355="","",VLOOKUP(B355,'Transacciones CHL'!$A$2:$F$14,4,FALSE)) | F355: =IF(B355="","",VLOOKUP(B355,'Transacciones CHL'!$A$2:$F$14,5,FALSE)) | G355: =IF(B355="","",VLOOKUP(B355,'Transacciones CHL'!$A$2:$F$14,6,FALSE))

Sheet FilasC
A1: Filas | B1: Áreas Transaccionales Filas No. | C1: Áreas Transaccionales Filas Descripción | D1: Codigo Transacción Filas | E1: Transacción filas | F1: Código Productos (CUP) | G1: Productos (CUP) | H1: Código Bioeconomía Productos | I1: Bioeconomía Productos | J1: Código CUPc | K1: CUPc
A2: mp_f001 | B2: ATF01 | C2: Producción | D2: P1 | E2: Producción | F2: 1 | G2: Trigo | H2: 1 | I2: Bioeconomía | J2: 2 | K2: No culturales
A3: mp_f002 | B3: ATF01 | C3: Producción | D3: P1 | E3: Producción | F3: 2 | G3: Maíz | H3: 1 | I3: Bioeconomía | J3: 2 | K3: No culturales
A4: mp_f003 | B4: ATF01 | C4: Producción | D4: P1 | E4: Producción | F4: 3 | G4: Otros cereales | H4: 1 | I4: Bioeconomía | J4: 2 | K4: No culturales
A5: mp_f004 | B5: ATF01 | C5: Producción | D5: P1 | E5: Producción | F5: 4 | G5: Tubérculos y legumbres | H5: 1 | I5: Bioeconomía | J5: 2 | K5: No culturales
A6: mp_f005 | B6: ATF01 | C6: Producción | D6: P1 | E6: Producción | F6: 5 | G6: Forrajeras y otros cultivos de uso industrial | H6: 1 | I6: Bioeconomía | J6: 2 | K6: No culturales
A7: mp_f006 | B7: ATF01 | C7: Producción | D7: P1 | E7: Producción | F7: 6 | G7: Hortalizas y setas | H7: 1 | I7: Bioeconomía | J7: 2 | K7: No culturales
A8: mp_f007 | B8: ATF01 | C8: Producción | D8: P1 | E8: Producción | F8: 7 | G8: Uva vinífera y pisquera | H8: 1 | I8: Bioeconomía | J8: 2 | K8: No culturales
A9: mp_f008 | B9: ATF01 | C9: Producción | D9: P1 | E9: Producción | F9: 8 | G9: Uva de mesa | H9: 1 | I9: Bioeconomía | J9: 2 | K9: No culturales
A10: mp_f009 | B10: ATF01 | C10: Producción | D10: P1 | E10: Producción | F10: 9 | G10: Manzanas | H10: 1 | I10: Bioeconomía | J10: 2 | K10: No culturales
A11: mp_f010 | B11: ATF01 | C11: Producción | D11: P1 | E11: Producción | F11: 10 | G11: Duraznos y otros carozos | H11: 1 | I11: Bioeconomía | J11: 2 | K11: No culturales
A12: mp_f011 | B12: ATF01 | C12: Producción | D12: P1 | E12: Producción | F12: 11 | G12: Paltas | H12: 1 | I12: Bioeconomía | J12: 2 | K12: No culturales
A13: mp_f012 | B13: ATF01 | C13: Producción | D13: P1 | E13: Producción | F13: 12 | G13: Kiwis y otras frutas tropicales | H13: 1 | I13: Bioeconomía | J13: 2 | K13: No culturales
... A725: ut_f181 | B725: ATF02 | C725: Consumo intermedio | D725: P2 | E725: Consumo intermedio | F725: 181 | G725: Otros bienes y servicios | H725: 3 | I725: No bioeconomía | J725: 2 | K725: No culturales
A726: va_f001 | B726: ATF06 | C726: Valor Agregado | D726: P91 | E726: Remuneraciones
A727: va_f002
A728: va_f003
A729: va_f004 | B729: ATF06 | C729: Valor Agregado | D729: P92 | E729: Excedente bruto de explotación
A730: va_f005
A731: va_f006
A732: va_f007 | B732: ATF06 | C732: Valor Agregado | D732: P93 | E732: Impuestos netos sobre los productos
A733: va_f008
A734: va_f009
A735: va_f010 | B735: ATF06 | C735: Valor Agregado | D735: P94 | E735: Otros impuestos netos sobre la producción

Sheet ColumnasC
A1: Columnas | B1: Código Transacciones | C1: Código área transaccional | D1: Área transaccional | E1: Transacciones | F1: Correlativo Transacciones Agregadas | G1: Código Transacciones Agregadas | H1: Transacciones Agregadas | I1: Código Subtransacción | J1: Subtransacción | K1: Código Actividades (CAE) | L1: Actividades (CAE) | M1: CIIU Secciones | N1: CIIU Secciones descripción | O1: CIIU Corto | P1: CIIU English | Q1: Correlativo Bioeconomía Actividades | R1: Bioeconomía Actividades | S1: Código CAEc | T1: CAEc
A2: mp_c001 | B2: P10 | C2: ATC01 | D2: Producción / Consumo intermedio | E2: Producción | F2: 1 | G2: P1 | H2: Producción | I2: 1 | J2: Producción | K2: 1 | L2: Cultivos anuales (cereales y otros) y forrajeras | M2: A | N2: Agricultura, ganadería, silvicultura y pesca | O2: Agricultura | P2: Agriculture, forestry and fishing | Q2: 1 | R2: Bioeconomía | S2: 2 | T2: No culturales
A3: mp_c002 | B3: P10 | C3: ATC01 | D3: Producción / Consumo intermedio | E3: Producción | F3: 1 | G3: P1 | H3: Producción | I3: 1 | J3: Producción | K3: 2 | L3: Cultivo de hortalizas y productos de viveros | M3: A | N3: Agricultura, ganadería, silvicultura y pesca | O3: Agricultura | P3: Agriculture, forestry and fishing | Q3: 1 | R3: Bioeconomía | S3: 2 | T3: No culturales
A4: mp_c003 | B4: P10 | C4: ATC01 | D4: Producción / Consumo intermedio | E4: Producción | F4: 1 | G4: P1 | H4: Producción | I4: 1 | J4: Producción | K4: 3 | L4: Cultivo de uva | M4: A | N4: Agricultura, ganadería, silvicultura y pesca | O4: Agricultura | P4: Agriculture, forestry and fishing | Q4: 1 | R4: Bioeconomía | S4: 2 | T4: No culturales
A5: mp_c004 | B5: P10 | C5: ATC01 | D5: Producción / Consumo intermedio | E5: Producción | F5: 1 | G5: P1 | H5: Producción | I5: 1 | J5: Producción | K5: 4 | L5: Cultivo de otras frutas | M5: A | N5: Agricultura, ganadería, silvicultura y pesca | O5: Agricultura | P5: Agriculture, forestry and fishing | Q5: 1 | R5: Bioeconomía | S5: 2 | T5: No culturales
A6: mp_c005 | B6: P10 | C6: ATC01 | D6: Producción / Consumo intermedio | E6: Producción | F6: 1 | G6: P1 | H6: Producción | I6: 1 | J6: Producción | K6: 5 | L6: Cría de ganado bovino | M6: A | N6: Agricultura, ganadería, silvicultura y pesca | O6: Agricultura | P6: Agriculture, forestry and fishing | Q6: 1 | R6: Bioeconomía | S6: 2 | T6: No culturales
A7: mp_c006 | B7: P10 | C7: ATC01 | D7: Producción / Consumo intermedio | E7: Producción | F7: 1 | G7: P1 | H7: Producción | I7: 1 | J7: Producción | K7: 6 | L7: Cría de cerdos | M7: A | N7: Agricultura, ganadería, silvicultura y pesca | O7: Agricultura | P7: Agriculture, forestry and fishing | Q7: 1 | R7: Bioeconomía | S7: 2 | T7: No culturales
A8: mp_c007 | B8: P10 | C8: ATC01 | D8: Producción / Consumo intermedio | E8: Producción | F8: 1 | G8: P1 | H8: Producción | I8: 1 | J8: Producción | K8: 7 | L8: Cría de aves de corral | M8: A | N8: Agricultura, ganadería, silvicultura y pesca | O8: Agricultura | P8: Agriculture, forestry and fishing | Q8: 1 | R8: Bioeconomía | S8: 2 | T8: No culturales
A9: mp_c008 | B9: P10 | C9: ATC01 | D9: Producción / Consumo intermedio | E9: Producción | F9: 1 | G9: P1 | H9: Producción | I9: 1 | J9: Producción | K9: 8 | L9: Cría de otros animales | M9: A | N9: Agricultura, ganadería, silvicultura y pesca | O9: Agricultura | P9: Agriculture, forestry and fishing | Q9: 1 | R9: Bioeconomía | S9: 2 | T9: No culturales
A10: mp_c009 | B10: P10 | C10: ATC01 | D10: Producción / Consumo intermedio | E10: Producción | F10: 1 | G10: P1 | H10: Producción | I10: 1 | J10: Producción | K10: 9 | L10: Actividades de apoyo a la agricultura y ganadería | M10: A | N10: Agricultura, ganadería, silvicultura y pesca | O10: Agricultura | P10: Agriculture, forestry and fishing | Q10: 1 | R10: Bioeconomía | S10: 2 | T10: No culturales
A11: mp_c010 | B11: P10 | C11: ATC01 | D11: Producción / Consumo intermedio | E11: Producción | F11: 1 | G11: P1 | H11: Producción | I11: 1 | J11: Producción | K11: 10 | L11: Silvicultura y extracción de madera | M11: A | N11: Agricultura, ganadería, silvicultura y pesca | O11: Agricultura | P11: Agriculture, forestry and fishing | Q11: 1 | R11: Bioeconomía | S11: 2 | T11: No culturales
A12: mp_c011 | B12: P10 | C12: ATC01 | D12: Producción / Consumo intermedio | E12: Producción | F12: 1 | G12: P1 | H12: Producción | I12: 1 | J12: Producción | K12: 11 | L12: Acuicultura | M12: A | N12: Agricultura, ganadería, silvicultura y pesca | O12: Agricultura | P12: Agriculture, forestry and fishing | Q12: 1 | R12: Bioeconomía | S12: 2 | T12: No culturales
A13: mp_c012 | B13: P10 | C13: ATC01 | D13: Producción / Consumo intermedio | E13: Producción | F13: 1 | G13: P1 | H13: Producción | I13: 1 | J13: Producción | K13: 12 | L13: Pesca extractiva | M13: A | N13: Agricultura, ganadería, silvicultura y pesca | O13: Agricultura | P13: Agriculture, forestry and fishing | Q13: 1 | R13: Bioeconomía | S13: 2 | T13: No culturales
... A112: mp_c111 | B112: P10 | C112: ATC01 | D112: Producción / Consumo intermedio | E112: Producción | F112: 1 | G112: P1 | H112: Producción | I112: 1 | J112: Producción | K112: 111 | L112: Otras actividades de servicios personales | M112: S | N112: Otras actividades de servicios | O112: Otros servicios | P112: Other service activities | Q112: 3 | R112: No bioeconomía | S112: 2 | T112: No culturales
A113: mp_c112
A114: ot_c001
A115: ot_c002 | B115: P70 | C115: ATC02 | D115: Exportaciones / Importaciones | E115: Importaciones de bienes Y SERVICIOS | F115: 7 | G115: P7 | H115: Importaciones de bienes y servicios | I115: 2 | J115: Importaciones precios cif
A116: ot_c003
A117: ot_c004 | B117: D214 | C117: ATC04 | D117: Impuestos menos subvenciones sobre los productos | E117: Impuestos sobre los productos, excepto IVA e impuestos sobre las importaciones | F117: 9 | G117: D2 | H117: Impuestos sobre la producción y las importaciones | I117: 3 | J117: Impuestos indirectos sobre bienes y servicios
A118: ot_c005 | B118: D212 | C118: ATC04 | D118: Impuestos menos subvenciones sobre los productos | E118: Impuestos y derechos sobre las importaciones excepto IVA | F118: 9 | G118: D2 | H118: Impuestos sobre la producción y las importaciones | I118: 4 | J118: Derechos de importación
A119: ot_c006
A120: ot_c007 | B120: M11 | C120: ATC05 | D120: Márgenes de distribución | E120: Márgenes de comercio | F120: 12 | G120: M1 | H120: Márgenes de distribución | I120: 5 | J120: Margen de comercio
A121: ot_c008 | B121: D211 | C121: ATC04 | D121: Impuestos menos subvenciones sobre los productos | E121: Impuestos tipo valor agregado (IVA) | F121: 9 | G121: D2 | H121: Impuestos sobre la producción y las importaciones | I121: 6 | J121: Impuesto al valor agregado
A122: ot_c009
A123: ui_c001 | B123: P20 | C123: ATC01 | D123: Producción / Consumo intermedio | E123: Consumo | F123: 2 | G123: P2 | H123: Consumo intermedio | I123: 1 | J123: Producción | K123: 1 | L123: Cultivos anuales (cereales y otros) y forrajeras | M123: A | N123: Agricultura, ganadería, silvicultura y pesca | O123: Agricultura | P123: Agriculture, forestry and fishing | Q123: 1 | R123: Bioeconomía | S123: 2 | T123: No culturales
A124: ui_c002 | B124: P20 | C124: ATC01 | D124: Producción / Consumo intermedio | E124: Consumo | F124: 2 | G124: P2 | H124: Consumo intermedio | I124: 1 | J124: Producción | K124: 2 | L124: Cultivo de hortalizas y productos de viveros | M124: A | N124: Agricultura, ganadería, silvicultura y pesca | O124: Agricultura | P124: Agriculture, forestry and fishing | Q124: 1 | R124: Bioeconomía | S124: 2 | T124: No culturales
A125: ui_c003 | B125: P20 | C125: ATC01 | D125: Producción / Consumo intermedio | E125: Consumo | F125: 2 | G125: P2 | H125: Consumo intermedio | I125: 1 | J125: Producción | K125: 3 | L125: Cultivo de uva | M125: A | N125: Agricultura, ganadería, silvicultura y pesca | O125: Agricultura | P125: Agriculture, forestry and fishing | Q125: 1 | R125: Bioeconomía | S125: 2 | T125: No culturales
A126: ui_c004 | B126: P20 | C126: ATC01 | D126: Producción / Consumo intermedio | E126: Consumo | F126: 2 | G126: P2 | H126: Consumo intermedio | I126: 1 | J126: Producción | K126: 4 | L126: Cultivo de otras frutas | M126: A | N126: Agricultura, ganadería, silvicultura y pesca | O126: Agricultura | P126: Agriculture, forestry and fishing | Q126: 1 | R126: Bioeconomía | S126: 2 | T126: No culturales
A127: ui_c005 | B127: P20 | C127: ATC01 | D127: Producción / Consumo intermedio | E127: Consumo | F127: 2 | G127: P2 | H127: Consumo intermedio | I127: 1 | J127: Producción | K127: 5 | L127: Cría de ganado bovino | M127: A | N127: Agricultura, ganadería, silvicultura y pesca | O127: Agricultura | P127: Agriculture, forestry and fishing | Q127: 1 | R127: Bioeconomía | S127: 2 | T127: No culturales
A128: ui_c006 | B128: P20 | C128: ATC01 | D128: Producción / Consumo intermedio | E128: Consumo | F128: 2 | G128: P2 | H128: Consumo intermedio | I128: 1 | J128: Producción | K128: 6 | L128: Cría de cerdos | M128: A | N128: Agricultura, ganadería, silvicultura y pesca | O128: Agricultura | P128: Agriculture, forestry and fishing | Q128: 1 | R128: Bioeconomía | S128: 2 | T128: No culturales
A129: ui_c007 | B129: P20 | C129: ATC01 | D129: Producción / Consumo intermedio | E129: Consumo | F129: 2 | G129: P2 | H129: Consumo intermedio | I129: 1 | J129: Producción | K129: 7 | L129: Cría de aves de corral | M129: A | N129: Agricultura, ganadería, silvicultura y pesca | O129: Agricultura | P129: Agriculture, forestry and fishing | Q129: 1 | R129: Bioeconomía | S129: 2 | T129: No culturales
A130: ui_c008 | B130: P20 | C130: ATC01 | D130: Producción / Consumo intermedio | E130: Consumo | F130: 2 | G130: P2 | H130: Consumo intermedio | I130: 1 | J130: Producción | K130: 8 | L130: Cría de otros animales | M130: A | N130: Agricultura, ganadería, silvicultura y pesca | O130: Agricultura | P130: Agriculture, forestry and fishing | Q130: 1 | R130: Bioeconomía | S130: 2 | T130: No culturales
A131: ui_c009 | B131: P20 | C131: ATC01 | D131: Producción / Consumo intermedio | E131: Consumo | F131: 2 | G131: P2 | H131: Consumo intermedio | I131: 1 | J131: Producción | K131: 9 | L131: Actividades de apoyo a la agricultura y ganadería | M131: A | N131: Agricultura, ganadería, silvicultura y pesca | O131: Agricultura | P131: Agriculture, forestry and fishing | Q131: 1 | R131: Bioeconomía | S131: 2 | T131: No culturales
A132: ui_c010 | B132: P20 | C132: ATC01 | D132: Producción / Consumo intermedio | E132: Consumo | F132: 2 | G132: P2 | H132: Consumo intermedio | I132: 1 | J132: Producción | K132: 10 | L132: Silvicultura y extracción de madera | M132: A | N132: Agricultura, ganadería, silvicultura y pesca | O132: Agricultura | P132: Agriculture, forestry and fishing | Q132: 1 | R132: Bioeconomía | S132: 2 | T132: No culturales
A133: ui_c011 | B133: P20 | C133: ATC01 | D133: Producción / Consumo intermedio | E133: Consumo | F133: 2 | G133: P2 | H133: Consumo intermedio | I133: 1 | J133: Producción | K133: 11 | L133: Acuicultura | M133: A | N133: Agricultura, ganadería, silvicultura y pesca | O133: Agricultura | P133: Agriculture, forestry and fishing | Q133: 1 | R133: Bioeconomía | S133: 2 | T133: No culturales
A134: ui_c012 | B134: P20 | C134: ATC01 | D134: Producción / Consumo intermedio | E134: Consumo | F134: 2 | G134: P2 | H134: Consumo intermedio | I134: 1 | J134: Producción | K134: 12 | L134: Pesca extractiva | M134: A | N134: Agricultura, ganadería, silvicultura y pesca | O134: Agricultura | P134: Agriculture, forestry and fishing | Q134: 1 | R134: Bioeconomía | S134: 2 | T134: No culturales
... A233: ui_c111 | B233: P20 | C233: ATC01 | D233: Producción / Consumo intermedio | E233: Consumo | F233: 2 | G233: P2 | H233: Consumo intermedio | I233: 1 | J233: Producción | K233: 111 | L233: Otras actividades de servicios personales | M233: S | N233: Otras actividades de servicios | O233: Otros servicios | P233: Other service activities | Q233: 3 | R233: No bioeconomía | S233: 2 | T233: No culturales
A234: ui_c112
A235: ut_c001
A236: ut_c002 | B236: Pa31 | C236: ATC06 | D236: Gasto de consumo final | E236: Gasto de consumo final de los hogares | F236: 3 | G236: P3 | H236: Gasto de consumo final | I236: 7 | J236: Consumo de hogares
A237: ut_c003 | B237: Pb30 | C237: ATC06 | D237: Consumo final | E237: Gasto de consumo ISFLH | F237: 3 | G237: P3 | H237: Gasto de consumo final | I237: 8 | J237: Consumo de IPSFL
A238: ut_c004 | B238: Pc30 | C238: ATC06 | D238: Consumo final | E238: Gasto de consumo de gobierno | F238: 3 | G238: P3 | H238: Gasto de consumo final | I238: 9 | J238: Consumo de gobierno
A239: ut_c005 | B239: P51b | C239: ATC07 | D239: Consumo final | E239: Formación bruta de capital fijo | F239: 5 | G239: P5 | H239: Formación de capital | I239: 10 | J239: Formación bruta de capital fijo
A240: ut_c006 | B240: P52 | C240: ATC07 | D240: Consumo final | E240: Variación de existencias | F240: 5 | G240: P5 | H240: Formación de capital | I240: 11 | J240: Variación de existencias
A241: ut_c007 | B241: P60 | C241: ATC02 | D241: Exportaciones / Importaciones | E241: Exportaciones de bienes y servicios | F241: 6 | G241: P6 | H241: Exportaciones de bienes y servicios | I241: 12 | J241: Exportaciones
A242: ut_c008
A243: ut_c009
A244: va_c001 | B244: P10 | C244: ATC01 | D244: Producción / Consumo intermedio | E244: Producción | F244: 1 | G244: P1 | H244: Producción | I244: 1 | J244: Producción | K244: 1 | L244: Cultivos anuales (cereales y otros) y forrajeras | M244: A | N244: Agricultura, ganadería, silvicultura y pesca | O244: Agricultura | P244: Agriculture, forestry and fishing | Q244: 1 | R244: Bioeconomía | S244: 2 | T244: No culturales
A245: va_c002 | B245: P10 | C245: ATC01 | D245: Producción / Consumo intermedio | E245: Producción | F245: 1 | G245: P1 | H245: Producción | I245: 1 | J245: Producción | K245: 2 | L245: Cultivo de hortalizas y productos de viveros | M245: A | N245: Agricultura, ganadería, silvicultura y pesca | O245: Agricultura | P245: Agriculture, forestry and fishing | Q245: 1 | R245: Bioeconomía | S245: 2 | T245: No culturales
A246: va_c003 | B246: P10 | C246: ATC01 | D246: Producción / Consumo intermedio | E246: Producción | F246: 1 | G246: P1 | H246: Producción | I246: 1 | J246: Producción | K246: 3 | L246: Cultivo de uva | M246: A | N246: Agricultura, ganadería, silvicultura y pesca | O246: Agricultura | P246: Agriculture, forestry and fishing | Q246: 1 | R246: Bioeconomía | S246: 2 | T246: No culturales
A247: va_c004 | B247: P10 | C247: ATC01 | D247: Producción / Consumo intermedio | E247: Producción | F247: 1 | G247: P1 | H247: Producción | I247: 1 | J247: Producción | K247: 4 | L247: Cultivo de otras frutas | M247: A | N247: Agricultura, ganadería, silvicultura y pesca | O247: Agricultura | P247: Agriculture, forestry and fishing | Q247: 1 | R247: Bioeconomía | S247: 2 | T247: No culturales
A248: va_c005 | B248: P10 | C248: ATC01 | D248: Producción / Consumo intermedio | E248: Producción | F248: 1 | G248: P1 | H248: Producción | I248: 1 | J248: Producción | K248: 5 | L248: Cría de ganado bovino | M248: A | N248: Agricultura, ganadería, silvicultura y pesca | O248: Agricultura | P248: Agriculture, forestry and fishing | Q248: 1 | R248: Bioeconomía | S248: 2 | T248: No culturales
A249: va_c006 | B249: P10 | C249: ATC01 | D249: Producción / Consumo intermedio | E249: Producción | F249: 1 | G249: P1 | H249: Producción | I249: 1 | J249: Producción | K249: 6 | L249: Cría de cerdos | M249: A | N249: Agricultura, ganadería, silvicultura y pesca | O249: Agricultura | P249: Agriculture, forestry and fishing | Q249: 1 | R249: Bioeconomía | S249: 2 | T249: No culturales
A250: va_c007 | B250: P10 | C250: ATC01 | D250: Producción / Consumo intermedio | E250: Producción | F250: 1 | G250: P1 | H250: Producción | I250: 1 | J250: Producción | K250: 7 | L250: Cría de aves de corral | M250: A | N250: Agricultura, ganadería, silvicultura y pesca | O250: Agricultura | P250: Agriculture, forestry and fishing | Q250: 1 | R250: Bioeconomía | S250: 2 | T250: No culturales
A251: va_c008 | B251: P10 | C251: ATC01 | D251: Producción / Consumo intermedio | E251: Producción | F251: 1 | G251: P1 | H251: Producción | I251: 1 | J251: Producción | K251: 8 | L251: Cría de otros animales | M251: A | N251: Agricultura, ganadería, silvicultura y pesca | O251: Agricultura | P251: Agriculture, forestry and fishing | Q251: 1 | R251: Bioeconomía | S251: 2 | T251: No culturales
A252: va_c009 | B252: P10 | C252: ATC01 | D252: Producción / Consumo intermedio | E252: Producción | F252: 1 | G252: P1 | H252: Producción | I252: 1 | J252: Producción | K252: 9 | L252: Actividades de apoyo a la agricultura y ganadería | M252: A | N252: Agricultura, ganadería, silvicultura y pesca | O252: Agricultura | P252: Agriculture, forestry and fishing | Q252: 1 | R252: Bioeconomía | S252: 2 | T252: No culturales
A253: va_c010 | B253: P10 | C253: ATC01 | D253: Producción / Consumo intermedio | E253: Producción | F253: 1 | G253: P1 | H253: Producción | I253: 1 | J253: Producción | K253: 10 | L253: Silvicultura y extracción de madera | M253: A | N253: Agricultura, ganadería, silvicultura y pesca | O253: Agricultura | P253: Agriculture, forestry and fishing | Q253: 1 | R253: Bioeconomía | S253: 2 | T253: No culturales
A254: va_c011 | B254: P10 | C254: ATC01 | D254: Producción / Consumo intermedio | E254: Producción | F254: 1 | G254: P1 | H254: Producción | I254: 1 | J254: Producción | K254: 11 | L254: Acuicultura | M254: A | N254: Agricultura, ganadería, silvicultura y pesca | O254: Agricultura | P254: Agriculture, forestry and fishing | Q254: 1 | R254: Bioeconomía | S254: 2 | T254: No culturales
A255: va_c012 | B255: P10 | C255: ATC01 | D255: Producción / Consumo intermedio | E255: Producción | F255: 1 | G255: P1 | H255: Producción | I255: 1 | J255: Producción | K255: 12 | L255: Pesca extractiva | M255: A | N255: Agricultura, ganadería, silvicultura y pesca | O255: Agricultura | P255: Agriculture, forestry and fishing | Q255: 1 | R255: Bioeconomía | S255: 2 | T255: No culturales
... A354: va_c111 | B354: P10 | C354: ATC01 | D354: Producción / Consumo intermedio | E354: Producción | F354: 1 | G354: P1 | H354: Producción | I354: 1 | J354: Producción | K354: 111 | L354: Otras actividades de servicios personales | M354: S | N354: Otras actividades de servicios | O354: Otros servicios | P354: Other service activities | Q354: 3 | R354: No bioeconomía | S354: 2 | T354: No culturales
A355: va_c112

Sheet Actividades
A1: Código Actividades (CAE) | B1: Actividades (CAE) | C1: Código Secciones CIIU | D1: Secciones CIIU | E1: Nombre Corto Secciones CIIU | F1: ISIC Sections (CIIU Inglés) | G1: Código Bioeconomía Actividades | H1: Bioeconomía Actividades | I1: Código CAEc | J1: CAEc
A2: 1 | B2: Cultivos anuales (cereales y otros) y forrajeras | C2: A | D2: Agricultura, ganadería, silvicultura y pesca | E2: Agricultura | F2: Agriculture, forestry and fishing | G2: 1 | H2: Bioeconomía | I2: 2 | J2: No culturales
A3: 2 | B3: Cultivo de hortalizas y productos de viveros | C3: A | D3: Agricultura, ganadería, silvicultura y pesca | E3: Agricultura | F3: Agriculture, forestry and fishing | G3: 1 | H3: Bioeconomía | I3: 2 | J3: No culturales
A4: 3 | B4: Cultivo de uva | C4: A | D4: Agricultura, ganadería, silvicultura y pesca | E4: Agricultura | F4: Agriculture, forestry and fishing | G4: 1 | H4: Bioeconomía | I4: 2 | J4: No culturales
A5: 4 | B5: Cultivo de otras frutas | C5: A | D5: Agricultura, ganadería, silvicultura y pesca | E5: Agricultura | F5: Agriculture, forestry and fishing | G5: 1 | H5: Bioeconomía | I5: 2 | J5: No culturales
A6: 5 | B6: Cría de ganado bovino | C6: A | D6: Agricultura, ganadería, silvicultura y pesca | E6: Agricultura | F6: Agriculture, forestry and fishing | G6: 1 | H6: Bioeconomía | I6: 2 | J6: No culturales
A7: 6 | B7: Cría de cerdos | C7: A | D7: Agricultura, ganadería, silvicultura y pesca | E7: Agricultura | F7: Agriculture, forestry and fishing | G7: 1 | H7: Bioeconomía | I7: 2 | J7: No culturales
A8: 7 | B8: Cría de aves de corral | C8: A | D8: Agricultura, ganadería, silvicultura y pesca | E8: Agricultura | F8: Agriculture, forestry and fishing | G8: 1 | H8: Bioeconomía | I8: 2 | J8: No culturales
A9: 8 | B9: Cría de otros animales | C9: A | D9: Agricultura, ganadería, silvicultura y pesca | E9: Agricultura | F9: Agriculture, forestry and fishing | G9: 1 | H9: Bioeconomía | I9: 2 | J9: No culturales
A10: 9 | B10: Actividades de apoyo a la agricultura y ganadería | C10: A | D10: Agricultura, ganadería, silvicultura y pesca | E10: Agricultura | F10: Agriculture, forestry and fishing | G10: 1 | H10: Bioeconomía | I10: 2 | J10: No culturales
A11: 10 | B11: Silvicultura y extracción de madera | C11: A | D11: Agricultura, ganadería, silvicultura y pesca | E11: Agricultura | F11: Agriculture, forestry and fishing | G11: 1 | H11: Bioeconomía | I11: 2 | J11: No culturales
A12: 11 | B12: Acuicultura | C12: A | D12: Agricultura, ganadería, silvicultura y pesca | E12: Agricultura | F12: Agriculture, forestry and fishing | G12: 1 | H12: Bioeconomía | I12: 2 | J12: No culturales
A13: 12 | B13: Pesca extractiva | C13: A | D13: Agricultura, ganadería, silvicultura y pesca | E13: Agricultura | F13: Agriculture, forestry and fishing | G13: 1 | H13: Bioeconomía | I13: 2 | J13: No culturales
... A112: 111 | B112: Otras actividades de servicios personales | C112: S | D112: Otras actividades de servicios | E112: Otros servicios | F112: Other service activities | G112: 3 | H112: No bioeconomía | I112: 2 | J112: No culturales
A113: 112 | B113: Actividades no especificada

Sheet Transacciones CHL
A1: Código Transacciones | B1: Transacciones | C1: Código Áreas Transaccionales | D1: Áreas Transaccionales | E1: Código ATC | F1: ATC
A2: 1 | B2: Producción bruta precio básico | C2: 1 | D2: Producción / Consumo intermedio | E2: 1 | F2: Producción / Consumo intermedio
A3: 2 | B3: Importaciones precios cif | C3: 2 | D3: Importaciones / Exportaciones | E3: 2 | F3: Importaciones / Exportaciones
A4: 3 | B4: Impuestos indirectos sobre bienes y servicios | C4: 3 | D4: Impuestos indirectos sobre bienes y servicios | E4: 3 | F4: Impuestos
A5: 4 | B5: Derechos de importación | C5: 4 | D5: Derechos de importación | E5: 3 | F5: Impuestos
A6: 5 | B6: Margen de comercio | C6: 5 | D6: Margen de comercio | E6: 4 | F6: Márgenes
A7: 6 | B7: Impuesto al valor agregado | C7: 6 | D7: Impuesto al valor agregado | E7: 3 | F7: Impuestos
A8: 7 | B8: Consumo intermedio | C8: 1 | D8: Producción / Consumo intermedio | E8: 1 | F8: Producción / Consumo intermedio
A9: 8 | B9: Consumo de hogares | C9: 7 | D9: Consumo de hogares | E9: 5 | F9: Consumo final
A10: 9 | B10: Consumo de IPSFL | C10: 8 | D10: Consumo de IPSFL | E10: 5 | F10: Consumo final
A11: 10 | B11: Consumo de gobierno | C11: 9 | D11: Consumo de gobierno | E11: 5 | F11: Consumo final
A12: 11 | B12: Formación bruta de capital fijo | C12: 10 | D12: Formación bruta de capital fijo | E12: 6 | F12: FBK / Variación existencias
A13: 12 | B13: Variación de existencias | C13: 11 | D13: Variación de existencias | E13: 6 | F13: FBK / Variación existencias
A14: 13 | B14: Exportaciones | C14: 2 | D14: Importaciones / Exportaciones | E14: 2 | F14: Importaciones / Exportaciones

Sheet Transacciones 
A1: Código Transacciones | B1: Código área transaccional | C1: Área transaccional | D1: Transacciones | E1: Correlativo Transacciones Agregadas | F1: Código Transacciones Agregadas | G1: Transacciones Agregadas | H1: corr_ntg2 | I1: id_area_columnas
A2: P10 | B2: ATC01 | C2: Producción / Consumo intermedio | D2: Producción | E2: 1 | F2: P1 | G2: Producción | H2: 1 | I2: 0
A3: P11 | B3: ATC01 | C3: Producción / Consumo intermedio | D3: Producción de mercado | E3: 1 | F3: P1 | G3: Producción | H3: 2 | I3: 1
A4: P12 | B4: ATC01 | C4: Producción / Consumo intermedio | D4: Producción para uso final propio | E4: 1 | F4: P1 | G4: Producción | H4: 3 | I4: 2
A5: P13 | B5: ATC01 | C5: Producción / Consumo intermedio | D5: Otra producción no de mercado | E5: 1 | F5: P1 | G5: Producción | H5: 4 | I5: 3
A6: P20 | B6: ATC01 | C6: Producción / Consumo intermedio | D6: Consumo | E6: 2 | F6: P2 | G6: Consumo intermedio | H6: 5 | I6: 0
A7: P21 | B7: ATC01 | C7: Producción / Consumo intermedio | D7: Consumo intermedio de mercado | E7: 2 | F7: P2 | G7: Consumo intermedio | H7: 6 | I7: 1
A8: P22 | B8: ATC01 | C8: Producción / Consumo intermedio | D8: Consumo intermedio para uso final propio | E8: 2 | F8: P2 | G8: Consumo intermedio | H8: 7 | I8: 2
A9: P23 | B9: ATC01 | C9: Producción / Consumo intermedio | D9: Consumo intermedio no de mercado | E9: 2 | F9: P2 | G9: Consumo intermedio | H9: 8 | I9: 3
A10: Pa31 | B10: ATC06 | C10: Gasto de consumo final | D10: Gasto de consumo final de los hogares | E10: 3 | F10: P3 | G10: Gasto de consumo final | H10: 9 | I10: 9
A11: Pb30 | B11: ATC06 | C11: Consumo final | D11: Gasto de consumo ISFLH | E11: 3 | F11: P3 | G11: Gasto de consumo final | H11: 10 | I11: 9
A12: Pb31 | B12: ATC06 | C12: Consumo final | D12: Gasto de consumo individual ISFLSH | E12: 3 | F12: P3 | G12: Gasto de consumo final | H12: 11 | I12: 9
A13: Pb32 | B13: ATC06 | C13: Consumo final | D13: Gasto de consumo colectivo ISFLSH | E13: 3 | F13: P3 | G13: Gasto de consumo final | H13: 12 | I13: 9
A14: Pc30 | B14: ATC06 | C14: Consumo final | D14: Gasto de consumo de gobierno | E14: 3 | F14: P3 | G14: Gasto de consumo final
A15: Pc31 | B15: ATC06 | C15: Consumo final | D15: Gasto de consumo individual de gobierno | E15: 3 | F15: P3 | G15: Gasto de consumo final | H15: 13 | I15: 9
A16: Pc32 | B16: ATC06 | C16: Consumo final | D16: Gasto de consumo colectivo de gobierno | E16: 3 | F16: P3 | G16: Gasto de consumo final | H16: 14 | I16: 9
A17: P41 | B17: ATC06 | C17: Consumo final | D17: Consumo individual efectivo | E17: 4 | F17: P4 | G17: Consumo final efectivo | H17: 15 | I17: 9
A18: P42 | B18: ATC06 | C18: Consumo final | D18: Consumo colectivo efectivo | E18: 4 | F18: P4 | G18: Consumo final efectivo | H18: 16 | I18: 9
A19: P51b | B19: ATC07 | C19: Consumo final | D19: Formación bruta de capital fijo | E19: 5 | F19: P5 | G19: Formación de capital | H19: 17 | I19: 10
A20: P51c | B20: ATC07 | C20: Consumo final | D20: Consumo de capital fijo | E20: 5 | F20: P5 | G20: Formación de capital | H20: 18 | I20: 10
A21: P52 | B21: ATC07 | C21: Consumo final | D21: Variación de existencias | E21: 5 | F21: P5 | G21: Formación de capital | H21: 19 | I21: 10
A22: P53 | B22: ATC07 | C22: Consumo final | D22: Adquisiciones menos disposiciones de objetos valiosos | E22: 5 | F22: P5 | G22: Formación de capital | H22: 20 | I22: 10
A23: P60 | B23: ATC02 | C23: Exportaciones / Importaciones | D23: Exportaciones de bienes y servicios | E23: 6 | F23: P6 | G23: Exportaciones de bienes y servicios | H23: 21 | I23: 4
A24: P61 | B24: ATC02 | C24: Exportaciones / Importaciones | D24: Exportaciones de bienes | E24: 6 | F24: P6 | G24: Exportaciones de bienes y servicios | H24: 22 | I24: 4
A25: P62 | B25: ATC02 | C25: Exportaciones / Importaciones | D25: Exportaciones de servicios | E25: 6 | F25: P6 | G25: Exportaciones de bienes y servicios | H25: 23 | I25: 4
A26: P70 | B26: ATC02 | C26: Exportaciones / Importaciones | D26: Importaciones de bienes Y SERVICIOS | E26: 7 | F26: P7 | G26: Importaciones de bienes y servicios | H26: 24 | I26: 4
... A39: M13 | B39: ATC05 | C39: Márgenes de distribución | D39: Márgenes de distribución de electricidad | E39: 12 | F39: M1 | G39: Márgenes de distribución | H39: 37 | I39: 8

Sheet Actividades sin C
A1: Código Actividades (CAE) | B1: Actividades (CAE) | C1: Código Secciones CIIU | D1: Secciones CIIU | E1: Nombre Corto Secciones CIIU | F1: ISIC Sections (CIIU Inglés) | G1: Código Bioeconomía Actividades | H1: Bioeconomía Actividades | I1: Código CAEc | J1: CAEc
A2: 1 | B2: Cultivos anuales (cereales y otros) y forrajeras | C2: A | D2: Agricultura, ganadería, silvicultura y pesca | E2: Agricultura | F2: Agriculture, forestry and fishing | G2: 1 | H2: Bioeconomía
A3: 2 | B3: Cultivo de hortalizas y productos de viveros | C3: A | D3: Agricultura, ganadería, silvicultura y pesca | E3: Agricultura | F3: Agriculture, forestry and fishing | G3: 1 | H3: Bioeconomía
A4: 3 | B4: Cultivo de uva | C4: A | D4: Agricultura, ganadería, silvicultura y pesca | E4: Agricultura | F4: Agriculture, forestry and fishing | G4: 1 | H4: Bioeconomía
A5: 4 | B5: Cultivo de otras frutas | C5: A | D5: Agricultura, ganadería, silvicultura y pesca | E5: Agricultura | F5: Agriculture, forestry and fishing | G5: 1 | H5: Bioeconomía
A6: 5 | B6: Cría de ganado bovino | C6: A | D6: Agricultura, ganadería, silvicultura y pesca | E6: Agricultura | F6: Agriculture, forestry and fishing | G6: 1 | H6: Bioeconomía
A7: 6 | B7: Cría de cerdos | C7: A | D7: Agricultura, ganadería, silvicultura y pesca | E7: Agricultura | F7: Agriculture, forestry and fishing | G7: 1 | H7: Bioeconomía
A8: 7 | B8: Cría de aves de corral | C8: A | D8: Agricultura, ganadería, silvicultura y pesca | E8: Agricultura | F8: Agriculture, forestry and fishing | G8: 1 | H8: Bioeconomía
A9: 8 | B9: Cría de otros animales | C9: A | D9: Agricultura, ganadería, silvicultura y pesca | E9: Agricultura | F9: Agriculture, forestry and fishing | G9: 1 | H9: Bioeconomía
A10: 9 | B10: Actividades de apoyo a la agricultura y ganadería | C10: A | D10: Agricultura, ganadería, silvicultura y pesca | E10: Agricultura | F10: Agriculture, forestry and fishing | G10: 1 | H10: Bioeconomía
A11: 10 | B11: Silvicultura y extracción de madera | C11: A | D11: Agricultura, ganadería, silvicultura y pesca | E11: Agricultura | F11: Agriculture, forestry and fishing | G11: 1 | H11: Bioeconomía
A12: 11 | B12: Acuicultura | C12: A | D12: Agricultura, ganadería, silvicultura y pesca | E12: Agricultura | F12: Agriculture, forestry and fishing | G12: 1 | H12: Bioeconomía
A13: 12 | B13: Pesca extractiva | C13: A | D13: Agricultura, ganadería, silvicultura y pesca | E13: Agricultura | F13: Agriculture, forestry and fishing | G13: 1 | H13: Bioeconomía
... A112: 111 | B112: Otras actividades de servicios personales | C112: S | D112: Otras actividades de servicios | E112: Otros servicios | F112: Other service activities | G112: 3 | H112: No bioeconomía
A113: 112 | B113: Actividades no especificada

Sheet Productos
A1: Código Productos (CUP) | B1: Productos (CUP) | C1: Código CPC Grupos | D1: CPC Grupos | E1: Código Productos Compactos | F1: Productos Compactos | G1: Código Bioeconomía Productos | H1: Bioeconomía Productos | I1: Código CUPc | J1: CUPc
A2: 1 | B2: Trigo | C2: ="0" -> 0 | D2: ="Productos de la agricultura, la silvicultura y la pesca" -> Productos de la agricultura, la silvicultura y la pesca | E2: 1 | F2: Agropecuarios | G2: 1 | H2: Bioeconomía | I2: 2 | J2: No culturales
A3: 2 | B3: Maíz | C3: ="0" -> 0 | D3: ="Productos de la agricultura, la silvicultura y la pesca" -> Productos de la agricultura, la silvicultura y la pesca | E3: 1 | F3: Agropecuarios | G3: 1 | H3: Bioeconomía | I3: 2 | J3: No culturales
A4: 3 | B4: Otros cereales | C4: ="0" -> 0 | D4: ="Productos de la agricultura, la silvicultura y la pesca" -> Productos de la agricultura, la silvicultura y la pesca | E4: 1 | F4: Agropecuarios | G4: 1 | H4: Bioeconomía | I4: 2 | J4: No culturales
A5: 4 | B5: Tubérculos y legumbres | C5: ="0" -> 0 | D5: ="Productos de la agricultura, la silvicultura y la pesca" -> Productos de la agricultura, la silvicultura y la pesca | E5: 1 | F5: Agropecuarios | G5: 1 | H5: Bioeconomía | I5: 2 | J5: No culturales
A6: 5 | B6: Forrajeras y otros cultivos de uso industrial | C6: ="0" -> 0 | D6: ="Productos de la agricultura, la silvicultura y la pesca" -> Productos de la agricultura, la silvicultura y la pesca | E6: 1 | F6: Agropecuarios | G6: 1 | H6: Bioeconomía | I6: 2 | J6: No culturales
A7: 6 | B7: Hortalizas y setas | C7: ="0" -> 0 | D7: ="Productos de la agricultura, la silvicultura y la pesca" -> Productos de la agricultura, la silvicultura y la pesca | E7: 1 | F7: Agropecuarios | G7: 1 | H7: Bioeconomía | I7: 2 | J7: No culturales
A8: 7 | B8: Uva vinífera y pisquera | C8: ="0" -> 0 | D8: ="Productos de la agricultura, la silvicultura y la pesca" -> Productos de la agricultura, la silvicultura y la pesca | E8: 1 | F8: Agropecuarios | G8: 1 | H8: Bioeconomía | I8: 2 | J8: No culturales
A9: 8 | B9: Uva de mesa | C9: ="0" -> 0 | D9: ="Productos de la agricultura, la silvicultura y la pesca" -> Productos de la agricultura, la silvicultura y la pesca | E9: 1 | F9: Agropecuarios | G9: 1 | H9: Bioeconomía | I9: 2 | J9: No culturales
A10: 9 | B10: Manzanas | C10: ="0" -> 0 | D10: ="Productos de la agricultura, la silvicultura y la pesca" -> Productos de la agricultura, la silvicultura y la pesca | E10: 1 | F10: Agropecuarios | G10: 1 | H10: Bioeconomía | I10: 2 | J10: No culturales
A11: 10 | B11: Duraznos y otros carozos | C11: ="0" -> 0 | D11: ="Productos de la agricultura, la silvicultura y la pesca" -> Productos de la agricultura, la silvicultura y la pesca | E11: 1 | F11: Agropecuarios | G11: 1 | H11: Bioeconomía | I11: 2 | J11: No culturales
A12: 11 | B12: Paltas | C12: ="0" -> 0 | D12: ="Productos de la agricultura, la silvicultura y la pesca" -> Productos de la agricultura, la silvicultura y la pesca | E12: 1 | F12: Agropecuarios | G12: 1 | H12: Bioeconomía | I12: 2 | J12: No culturales
A13: 12 | B13: Kiwis y otras frutas tropicales | C13: ="0" -> 0 | D13: ="Productos de la agricultura, la silvicultura y la pesca" -> Productos de la agricultura, la silvicultura y la pesca | E13: 1 | F13: Agropecuarios | G13: 1 | H13: Bioeconomía | I13: 2 | J13: No culturales
... A27: 26 | B27: Otros pescados, mariscos y algas | C27: ="0" -> 0 | D27: ="Productos de la agricultura, la silvicultura y la pesca" -> Productos de la agricultura, la silvicultura y la pesca | E27: 1 | F27: Agropecuarios | G27: 1 | H27: Bioeconomía | I27: 2 | J27: No culturales
A28: 27 | B28: Carbón | C28: ="1" -> 1 | D28: ="Minerales; electricidad, gas y agua" -> Minerales; electricidad, gas y agua | E28: 2 | F28: Minería | G28: 3 | H28: No bioeconomía | I28: 2 | J28: No culturales
A29: 28 | B29: Petróleo crudo | C29: ="1" -> 1 | D29: ="Minerales; electricidad, gas y agua" -> Minerales; electricidad, gas y agua | E29: 2 | F29: Minería | G29: 3 | H29: No bioeconomía | I29: 2 | J29: No culturales
A30: 29 | B30: Gas natural | C30: ="1" -> 1 | D30: ="Minerales; electricidad, gas y agua" -> Minerales; electricidad, gas y agua | E30: 2 | F30: Minería | G30: 3 | H30: No bioeconomía | I30: 2 | J30: No culturales
A31: 30 | B31: Cobre | C31: ="1" -> 1 | D31: ="Minerales; electricidad, gas y agua" -> Minerales; electricidad, gas y agua | E31: 2 | F31: Minería | G31: 3 | H31: No bioeconomía | I31: 2 | J31: No culturales
A32: 31 | B32: Minerales de molibdeno y sus concentrados | C32: ="1" -> 1 | D32: ="Minerales; electricidad, gas y agua" -> Minerales; electricidad, gas y agua | E32: 2 | F32: Minería | G32: 3 | H32: No bioeconomía | I32: 2 | J32: No culturales
A33: 32 | B33: Hierro | C33: ="1" -> 1 | D33: ="Minerales; electricidad, gas y agua" -> Minerales; electricidad, gas y agua | E33: 2 | F33: Minería | G33: 3 | H33: No bioeconomía | I33: 2 | J33: No culturales
A34: 33 | B34: Oro | C34: ="1" -> 1 | D34: ="Minerales; electricidad, gas y agua" -> Minerales; electricidad, gas y agua | E34: 2 | F34: Minería | G34: 3 | H34: No bioeconomía | I34: 2 | J34: No culturales
A35: 34 | B35: Plata y otros metalíferos no ferrosos | C35: ="1" -> 1 | D35: ="Minerales; electricidad, gas y agua" -> Minerales; electricidad, gas y agua | E35: 2 | F35: Minería | G35: 3 | H35: No bioeconomía | I35: 2 | J35: No culturales
A36: 35 | B36: Minerales no metálicos | C36: ="1" -> 1 | D36: ="Minerales; electricidad, gas y agua" -> Minerales; electricidad, gas y agua | E36: 2 | F36: Minería | G36: 3 | H36: No bioeconomía | I36: 2 | J36: No culturales
A37: 36 | B37: Servicios de exploración minera | C37: ="1" -> 1 | D37: ="Minerales; electricidad, gas y agua" -> Minerales; electricidad, gas y agua | E37: 2 | F37: Minería | G37: 3 | H37: No bioeconomía | I37: 2 | J37: No culturales
A38: 37 | B38: Carne de bovino | C38: ="2" -> 2 | D38: ="Productos alimenticios, bebidas y tabaco; textiles, prendas de vestir y productos de cuero" -> Productos alimenticios, bebidas y tabaco; textiles, prendas de vestir y productos de cuero | E38: 3 | F38: Manufacturas | G38: 1 | H38: Bioeconomía | I38: 2 | J38: No culturales
A39: 38 | B39: Carne de porcino | C39: ="2" -> 2 | D39: ="Productos alimenticios, bebidas y tabaco; textiles, prendas de vestir y productos de cuero" -> Productos alimenticios, bebidas y tabaco; textiles, prendas de vestir y productos de cuero | E39: 3 | F39: Manufacturas | G39: 1 | H39: Bioeconomía | I39: 2 | J39: No culturales
A40: 39 | B40: Carne de ave | C40: ="2" -> 2 | D40: ="Productos alimenticios, bebidas y tabaco; textiles, prendas de vestir y productos de cuero" -> Productos alimenticios, bebidas y tabaco; textiles, prendas de vestir y productos de cuero | E40: 3 | F40: Manufacturas | G40: 1 | H40: Bioeconomía | I40: 2 | J40: No culturales
A41: 40 | B41: Cecinas y otras carnes | C41: ="2" -> 2 | D41: ="Productos alimenticios, bebidas y tabaco; textiles, prendas de vestir y productos de cuero" -> Productos alimenticios, bebidas y tabaco; textiles, prendas de vestir y productos de cuero | E41: 3 | F41: Manufacturas | G41: 1 | H41: Bioeconomía | I41: 2 | J41: No culturales
A42: 41 | B42: Harina de pescado | C42: ="2" -> 2 | D42: ="Productos alimenticios, bebidas y tabaco; textiles, prendas de vestir y productos de cuero" -> Productos alimenticios, bebidas y tabaco; textiles, prendas de vestir y productos de cuero | E42: 3 | F42: Manufacturas | G42: 1 | H42: Bioeconomía | I42: 2 | J42: No culturales
A43: 42 | B43: Aceite de pescado | C43: ="2" -> 2 | D43: ="Productos alimenticios, bebidas y tabaco; textiles, prendas de vestir y productos de cuero" -> Productos alimenticios, bebidas y tabaco; textiles, prendas de vestir y productos de cuero | E43: 3 | F43: Manufacturas | G43: 1 | H43: Bioeconomía | I43: 2 | J43: No culturales
A44: 43 | B44: Salmon y trucha refrigerados o congelados | C44: ="2" -> 2 | D44: ="Productos alimenticios, bebidas y tabaco; textiles, prendas de vestir y productos de cuero" -> Productos alimenticios, bebidas y tabaco; textiles, prendas de vestir y productos de cuero | E44: 3 | F44: Manufacturas | G44: 1 | H44: Bioeconomía | I44: 2 | J44: No culturales
A45: 44 | B45: Otros pescados refrigerados o congelados | C45: ="2" -> 2 | D45: ="Productos alimenticios, bebidas y tabaco; textiles, prendas de vestir y productos de cuero" -> Productos alimenticios, bebidas y tabaco; textiles, prendas de vestir y productos de cuero | E45: 3 | F45: Manufacturas | G45: 1 | H45: Bioeconomía | I45: 2 | J45: No culturales
A46: 45 | B46: Conservas de pescados y mariscos | C46: ="2" -> 2 | D46: ="Productos alimenticios, bebidas y tabaco; textiles, prendas de vestir y productos de cuero" -> Productos alimenticios, bebidas y tabaco; textiles, prendas de vestir y productos de cuero | E46: 3 | F46: Manufacturas | G46: 1 | H46: Bioeconomía | I46: 2 | J46: No culturales
A47: 46 | B47: Conservas de frutas y vegetales | C47: ="2" -> 2 | D47: ="Productos alimenticios, bebidas y tabaco; textiles, prendas de vestir y productos de cuero" -> Productos alimenticios, bebidas y tabaco; textiles, prendas de vestir y productos de cuero | E47: 3 | F47: Manufacturas | G47: 1 | H47: Bioeconomía | I47: 2 | J47: No culturales
A48: 47 | B48: Otros aceites y grasas | C48: ="2" -> 2 | D48: ="Productos alimenticios, bebidas y tabaco; textiles, prendas de vestir y productos de cuero" -> Productos alimenticios, bebidas y tabaco; textiles, prendas de vestir y productos de cuero | E48: 3 | F48: Manufacturas | G48: 1 | H48: Bioeconomía | I48: 2 | J48: No culturales
A49: 48 | B49: Leche elaborada | C49: ="2" -> 2 | D49: ="Productos alimenticios, bebidas y tabaco; textiles, prendas de vestir y productos de cuero" -> Productos alimenticios, bebidas y tabaco; textiles, prendas de vestir y productos de cuero | E49: 3 | F49: Manufacturas | G49: 1 | H49: Bioeconomía | I49: 2 | J49: No culturales
... A68: 67 | B68: Calzado | C68: ="2" -> 2 | D68: ="Productos alimenticios, bebidas y tabaco; textiles, prendas de vestir y productos de cuero" -> Productos alimenticios, bebidas y tabaco; textiles, prendas de vestir y productos de cuero | E68: 3 | F68: Manufacturas | G68: 2 | H68: Bioeconomía extendida | I68: 2 | J68: No culturales
A69: 68 | B69: Madera aserrada, cepillada y astillada | C69: ="3" -> 3 | D69: ="Otros bienes transportables, excepto productos metálicos, maquinaria y equipo" -> Otros bienes transportables, excepto productos metálicos, maquinaria y equipo | E69: 3 | F69: Manufacturas | G69: 2 | H69: Bioeconomía extendida | I69: 2 | J69: No culturales
A70: 69 | B70: Tableros y madera prensada | C70: ="3" -> 3 | D70: ="Otros bienes transportables, excepto productos metálicos, maquinaria y equipo" -> Otros bienes transportables, excepto productos metálicos, maquinaria y equipo | E70: 3 | F70: Manufacturas | G70: 2 | H70: Bioeconomía extendida | I70: 2 | J70: No culturales
A71: 70 | B71: Otros productos de madera | C71: ="3" -> 3 | D71: ="Otros bienes transportables, excepto productos metálicos, maquinaria y equipo" -> Otros bienes transportables, excepto productos metálicos, maquinaria y equipo | E71: 3 | F71: Manufacturas | G71: 2 | H71: Bioeconomía extendida | I71: 2 | J71: No culturales
A72: 71 | B72: Celulosa | C72: ="3" -> 3 | D72: ="Otros bienes transportables, excepto productos metálicos, maquinaria y equipo" -> Otros bienes transportables, excepto productos metálicos, maquinaria y equipo | E72: 3 | F72: Manufacturas | G72: 2 | H72: Bioeconomía extendida | I72: 2 | J72: No culturales
A73: 72 | B73: Papel periódico | C73: ="3" -> 3 | D73: ="Otros bienes transportables, excepto productos metálicos, maquinaria y equipo" -> Otros bienes transportables, excepto productos metálicos, maquinaria y equipo | E73: 3 | F73: Manufacturas | G73: 2 | H73: Bioeconomía extendida | I73: 2 | J73: No culturales
A74: 73 | B74: Envases de papel y cartón | C74: ="3" -> 3 | D74: ="Otros bienes transportables, excepto productos metálicos, maquinaria y equipo" -> Otros bienes transportables, excepto productos metálicos, maquinaria y equipo | E74: 3 | F74: Manufacturas | G74: 2 | H74: Bioeconomía extendida | I74: 2 | J74: No culturales
A75: 74 | B75: Productos tissue | C75: ="3" -> 3 | D75: ="Otros bienes transportables, excepto productos metálicos, maquinaria y equipo" -> Otros bienes transportables, excepto productos metálicos, maquinaria y equipo | E75: 3 | F75: Manufacturas | G75: 2 | H75: Bioeconomía extendida | I75: 2 | J75: No culturales
A76: 75 | B76: Otros papeles y cartones | C76: ="3" -> 3 | D76: ="Otros bienes transportables, excepto productos metálicos, maquinaria y equipo" -> Otros bienes transportables, excepto productos metálicos, maquinaria y equipo | E76: 3 | F76: Manufacturas | G76: 2 | H76: Bioeconomía extendida | I76: 2 | J76: No culturales
A77: 76 | B77: Libros, diarios, revistas y otros impresos | C77: ="3" -> 3 | D77: ="Otros bienes transportables, excepto productos metálicos, maquinaria y equipo" -> Otros bienes transportables, excepto productos metálicos, maquinaria y equipo | E77: 3 | F77: Manufacturas | G77: 3 | H77: No bioeconomía | I77: 1 | J77: Culturales
A78: 77 | B78: Diésel | C78: ="3" -> 3 | D78: ="Otros bienes transportables, excepto productos metálicos, maquinaria y equipo" -> Otros bienes transportables, excepto productos metálicos, maquinaria y equipo | E78: 3 | F78: Manufacturas | G78: 3 | H78: No bioeconomía | I78: 2 | J78: No culturales
A79: 78 | B79: Gasolinas | C79: ="3" -> 3 | D79: ="Otros bienes transportables, excepto productos metálicos, maquinaria y equipo" -> Otros bienes transportables, excepto productos metálicos, maquinaria y equipo | E79: 3 | F79: Manufacturas | G79: 3 | H79: No bioeconomía | I79: 2 | J79: No culturales
A80: 79 | B80: Kerosene | C80: ="3" -> 3 | D80: ="Otros bienes transportables, excepto productos metálicos, maquinaria y equipo" -> Otros bienes transportables, excepto productos metálicos, maquinaria y equipo | E80: 3 | F80: Manufacturas | G80: 3 | H80: No bioeconomía | I80: 2 | J80: No culturales
... A98: 97 | B98: Otros productos de minerales no metálicos | C98: ="3" -> 3 | D98: ="Otros bienes transportables, excepto productos metálicos, maquinaria y equipo" -> Otros bienes transportables, excepto productos metálicos, maquinaria y equipo | E98: 3 | F98: Manufacturas | G98: 3 | H98: No bioeconomía | I98: 2 | J98: No culturales
A99: 98 | B99: Ferromolibdeno y otros productos básicos de acero | C99: ="4" -> 4 | D99: ="Productos metálicos, maquinaria y equipo" -> Productos metálicos, maquinaria y equipo | E99: 3 | F99: Manufacturas | G99: 3 | H99: No bioeconomía | I99: 2 | J99: No culturales
A100: 99 | B100: Productos de hierro y acero | C100: ="4" -> 4 | D100: ="Productos metálicos, maquinaria y equipo" -> Productos metálicos, maquinaria y equipo | E100: 3 | F100: Manufacturas | G100: 3 | H100: No bioeconomía | I100: 2 | J100: No culturales
A101: 100 | B101: Productos básicos de metales no ferrosos | C101: ="4" -> 4 | D101: ="Productos metálicos, maquinaria y equipo" -> Productos metálicos, maquinaria y equipo | E101: 3 | F101: Manufacturas | G101: 3 | H101: No bioeconomía | I101: 2 | J101: No culturales
A102: 101 | B102: Productos metálicos de uso estructural | C102: ="4" -> 4 | D102: ="Productos metálicos, maquinaria y equipo" -> Productos metálicos, maquinaria y equipo | E102: 3 | F102: Manufacturas | G102: 3 | H102: No bioeconomía | I102: 2 | J102: No culturales
A103: 102 | B103: Otros productos metálicos | C103: ="4" -> 4 | D103: ="Productos metálicos, maquinaria y equipo" -> Productos metálicos, maquinaria y equipo | E103: 3 | F103: Manufacturas | G103: 3 | H103: No bioeconomía | I103: 2 | J103: No culturales
A104: 103 | B104: Maquinaria para uso industrial | C104: ="4" -> 4 | D104: ="Productos metálicos, maquinaria y equipo" -> Productos metálicos, maquinaria y equipo | E104: 3 | F104: Manufacturas | G104: 3 | H104: No bioeconomía | I104: 2 | J104: No culturales
A105: 104 | B105: Computadores y sus componentes | C105: ="4" -> 4 | D105: ="Productos metálicos, maquinaria y equipo" -> Productos metálicos, maquinaria y equipo | E105: 3 | F105: Manufacturas | G105: 3 | H105: No bioeconomía | I105: 2 | J105: No culturales
A106: 105 | B106: Otras maquinarias de oficina | C106: ="4" -> 4 | D106: ="Productos metálicos, maquinaria y equipo" -> Productos metálicos, maquinaria y equipo | E106: 3 | F106: Manufacturas | G106: 3 | H106: No bioeconomía | I106: 2 | J106: No culturales
A107: 106 | B107: Televisores | C107: ="4" -> 4 | D107: ="Productos metálicos, maquinaria y equipo" -> Productos metálicos, maquinaria y equipo | E107: 3 | F107: Manufacturas | G107: 3 | H107: No bioeconomía | I107: 1 | J107: Culturales
A108: 107 | B108: Teléfonos móviles | C108: ="4" -> 4 | D108: ="Productos metálicos, maquinaria y equipo" -> Productos metálicos, maquinaria y equipo | E108: 3 | F108: Manufacturas | G108: 3 | H108: No bioeconomía | I108: 2 | J108: No culturales
A109: 108 | B109: Máquinas y aparatos de uso doméstico | C109: ="4" -> 4 | D109: ="Productos metálicos, maquinaria y equipo" -> Productos metálicos, maquinaria y equipo | E109: 3 | F109: Manufacturas | G109: 3 | H109: No bioeconomía | I109: 2 | J109: No culturales
A110: 109 | B110: Otras maquinarias y equipos eléctricos | C110: ="4" -> 4 | D110: ="Productos metálicos, maquinaria y equipo" -> Productos metálicos, maquinaria y equipo | E110: 3 | F110: Manufacturas | G110: 3 | H110: No bioeconomía | I110: 1 | J110: Culturales
... A119: 118 | B119: Servicios de mantenimiento y reparación de equipo de transporte | C119: ="4" -> 4 | D119: ="Productos metálicos, maquinaria y equipo" -> Productos metálicos, maquinaria y equipo | E119: 3 | F119: Manufacturas | G119: 3 | H119: No bioeconomía | I119: 2 | J119: No culturales
A120: 119 | B120: Energía y potencia eléctrica | C120: ="1" -> 1 | D120: ="Minerales; electricidad, gas y agua" -> Minerales; electricidad, gas y agua | E120: 4 | F120: Servicios básicos | G120: 3 | H120: No bioeconomía | I120: 2 | J120: No culturales
A121: 120 | B121: Servicios de transmisión de electricidad | C121: ="1" -> 1 | D121: ="Minerales; electricidad, gas y agua" -> Minerales; electricidad, gas y agua | E121: 4 | F121: Servicios básicos | G121: 3 | H121: No bioeconomía | I121: 2 | J121: No culturales
A122: 121 | B122: Servicios de distribución de electricidad | C122: ="1" -> 1 | D122: ="Minerales; electricidad, gas y agua" -> Minerales; electricidad, gas y agua | E122: 4 | F122: Servicios básicos | G122: 3 | H122: No bioeconomía | I122: 2 | J122: No culturales
A123: 122 | B123: Gas distribuido por ductos | C123: ="1" -> 1 | D123: ="Minerales; electricidad, gas y agua" -> Minerales; electricidad, gas y agua | E123: 4 | F123: Servicios básicos | G123: 3 | H123: No bioeconomía | I123: 2 | J123: No culturales
A124: 123 | B124: Agua | C124: ="1" -> 1 | D124: ="Minerales; electricidad, gas y agua" -> Minerales; electricidad, gas y agua | E124: 4 | F124: Servicios básicos | G124: 2 | H124: Bioeconomía extendida | I124: 2 | J124: No culturales
A125: 124 | B125: Servicios de eliminación de desperdicios y reciclaje | C125: ="1" -> 1 | D125: ="Minerales; electricidad, gas y agua" -> Minerales; electricidad, gas y agua | E125: 4 | F125: Servicios básicos | G125: 2 | H125: Bioeconomía extendida | I125: 2 | J125: No culturales
A126: 125 | B126: Edificios residenciales | C126: ="5" -> 5 | D126: ="Construcciones y servicios de construcción" -> Construcciones y servicios de construcción | E126: 5 | F126: Construcción | G126: 3 | H126: No bioeconomía | I126: 2 | J126: No culturales
A127: 126 | B127: Edificios no residenciales | C127: ="5" -> 5 | D127: ="Construcciones y servicios de construcción" -> Construcciones y servicios de construcción | E127: 5 | F127: Construcción | G127: 3 | H127: No bioeconomía | I127: 2 | J127: No culturales
A128: 127 | B128: Obras viales | C128: ="5" -> 5 | D128: ="Construcciones y servicios de construcción" -> Construcciones y servicios de construcción | E128: 5 | F128: Construcción | G128: 3 | H128: No bioeconomía | I128: 2 | J128: No culturales
A129: 128 | B129: Obras de proyectos de energía eléctrica | C129: ="5" -> 5 | D129: ="Construcciones y servicios de construcción" -> Construcciones y servicios de construcción | E129: 5 | F129: Construcción | G129: 3 | H129: No bioeconomía | I129: 2 | J129: No culturales
A130: 129 | B130: Obras mineras | C130: ="5" -> 5 | D130: ="Construcciones y servicios de construcción" -> Construcciones y servicios de construcción | E130: 5 | F130: Construcción | G130: 3 | H130: No bioeconomía | I130: 2 | J130: No culturales
A131: 130 | B131: Otras obras de ingeniería | C131: ="5" -> 5 | D131: ="Construcciones y servicios de construcción" -> Construcciones y servicios de construcción | E131: 5 | F131: Construcción | G131: 3 | H131: No bioeconomía | I131: 2 | J131: No culturales
A132: 131 | B132: Servicios de construcción | C132: ="5" -> 5 | D132: ="Construcciones y servicios de construcción" -> Construcciones y servicios de construcción | E132: 5 | F132: Construcción | G132: 3 | H132: No bioeconomía | I132: 2 | J132: No culturales
A133: 132 | B133: Servicios comerciales de intermediación automotriz | C133: ="6" -> 6 | D133: ="Servicios comerciales de distribución; alojamiento, servicios de suministro de comidas y bebidas; servicios de transporte; y servicios de distribución de electricidad, gas y agua" -> Servicios comerciales de distribución; alojamiento, servicios de suministro de comidas y bebidas; servicios de transporte; y servicios de distribución de electricidad, gas y agua | E133: 6 | F133: Comercio | G133: 3 | H133: No bioeconomía | I133: 2 | J133: No culturales
A134: 133 | B134: Servicios comerciales de intermediación mayorista | C134: ="6" -> 6 | D134: ="Servicios comerciales de distribución; alojamiento, servicios de suministro de comidas y bebidas; servicios de transporte; y servicios de distribución de electricidad, gas y agua" -> Servicios comerciales de distribución; alojamiento, servicios de suministro de comidas y bebidas; servicios de transporte; y servicios de distribución de electricidad, gas y agua | E134: 6 | F134: Comercio | G134: 3 | H134: No bioeconomía | I134: 2 | J134: No culturales
A135: 134 | B135: Servicios comerciales de intermediación minorista | C135: ="6" -> 6 | D135: ="Servicios comerciales de distribución; alojamiento, servicios de suministro de comidas y bebidas; servicios de transporte; y servicios de distribución de electricidad, gas y agua" -> Servicios comerciales de distribución; alojamiento, servicios de suministro de comidas y bebidas; servicios de transporte; y servicios de distribución de electricidad, gas y agua | E135: 6 | F135: Comercio | G135: 3 | H135: No bioeconomía | I135: 1 | J135: Culturales
A136: 135 | B136: Servicios comerciales a cambio de una retribución o por contrata | C136: ="6" -> 6 | D136: ="Servicios comerciales de distribución; alojamiento, servicios de suministro de comidas y bebidas; servicios de transporte; y servicios de distribución de electricidad, gas y agua" -> Servicios comerciales de distribución; alojamiento, servicios de suministro de comidas y bebidas; servicios de transporte; y servicios de distribución de electricidad, gas y agua | E136: 6 | F136: Comercio | G136: 3 | H136: No bioeconomía | I136: 2 | J136: No culturales
A137: 136 | B137: Servicios de mantenimiento y reparación de vehículos automotores | C137: ="6" -> 6 | D137: ="Servicios comerciales de distribución; alojamiento, servicios de suministro de comidas y bebidas; servicios de transporte; y servicios de distribución de electricidad, gas y agua" -> Servicios comerciales de distribución; alojamiento, servicios de suministro de comidas y bebidas; servicios de transporte; y servicios de distribución de electricidad, gas y agua | E137: 7 | F137: Otros servicios | G137: 3 | H137: No bioeconomía | I137: 2 | J137: No culturales
A138: 137 | B138: Servicios de hotelería | C138: ="6" -> 6 | D138: ="Servicios comerciales de distribución; alojamiento, servicios de suministro de comidas y bebidas; servicios de transporte; y servicios de distribución de electricidad, gas y agua" -> Servicios comerciales de distribución; alojamiento, servicios de suministro de comidas y bebidas; servicios de transporte; y servicios de distribución de electricidad, gas y agua | E138: 7 | F138: Otros servicios | G138: 3 | H138: No bioeconomía | I138: 2 | J138: No culturales
A139: 138 | B139: Servicios de restaurantes | C139: ="6" -> 6 | D139: ="Servicios comerciales de distribución; alojamiento, servicios de suministro de comidas y bebidas; servicios de transporte; y servicios de distribución de electricidad, gas y agua" -> Servicios comerciales de distribución; alojamiento, servicios de suministro de comidas y bebidas; servicios de transporte; y servicios de distribución de electricidad, gas y agua | E139: 7 | F139: Otros servicios | G139: 2 | H139: Bioeconomía extendida | I139: 2 | J139: No culturales
A140: 139 | B140: Servicios de transporte por ferrocarril | C140: ="6" -> 6 | D140: ="Servicios comerciales de distribución; alojamiento, servicios de suministro de comidas y bebidas; servicios de transporte; y servicios de distribución de electricidad, gas y agua" -> Servicios comerciales de distribución; alojamiento, servicios de suministro de comidas y bebidas; servicios de transporte; y servicios de distribución de electricidad, gas y agua | E140: 7 | F140: Otros servicios | G140: 3 | H140: No bioeconomía | I140: 2 | J140: No culturales
A141: 140 | B141: Servicios de transporte caminero de pasajeros | C141: ="6" -> 6 | D141: ="Servicios comerciales de distribución; alojamiento, servicios de suministro de comidas y bebidas; servicios de transporte; y servicios de distribución de electricidad, gas y agua" -> Servicios comerciales de distribución; alojamiento, servicios de suministro de comidas y bebidas; servicios de transporte; y servicios de distribución de electricidad, gas y agua | E141: 7 | F141: Otros servicios | G141: 3 | H141: No bioeconomía | I141: 2 | J141: No culturales
A142: 141 | B142: Servicios de transporte caminero de carga | C142: ="6" -> 6 | D142: ="Servicios comerciales de distribución; alojamiento, servicios de suministro de comidas y bebidas; servicios de transporte; y servicios de distribución de electricidad, gas y agua" -> Servicios comerciales de distribución; alojamiento, servicios de suministro de comidas y bebidas; servicios de transporte; y servicios de distribución de electricidad, gas y agua | E142: 7 | F142: Otros servicios | G142: 3 | H142: No bioeconomía | I142: 2 | J142: No culturales
A143: 142 | B143: Transporte por tuberías (gasoductos y oleoductos) | C143: ="6" -> 6 | D143: ="Servicios comerciales de distribución; alojamiento, servicios de suministro de comidas y bebidas; servicios de transporte; y servicios de distribución de electricidad, gas y agua" -> Servicios comerciales de distribución; alojamiento, servicios de suministro de comidas y bebidas; servicios de transporte; y servicios de distribución de electricidad, gas y agua | E143: 7 | F143: Otros servicios | G143: 3 | H143: No bioeconomía | I143: 2 | J143: No culturales
A144: 143 | B144: Servicios de transporte marítimo | C144: ="6" -> 6 | D144: ="Servicios comerciales de distribución; alojamiento, servicios de suministro de comidas y bebidas; servicios de transporte; y servicios de distribución de electricidad, gas y agua" -> Servicios comerciales de distribución; alojamiento, servicios de suministro de comidas y bebidas; servicios de transporte; y servicios de distribución de electricidad, gas y agua | E144: 7 | F144: Otros servicios | G144: 3 | H144: No bioeconomía | I144: 2 | J144: No culturales
... A157: 156 | B157: Servicios de edición, producción y difusión | C157: ="6" -> 6 | D157: ="Servicios comerciales de distribución; alojamiento, servicios de suministro de comidas y bebidas; servicios de transporte; y servicios de distribución de electricidad, gas y agua" -> Servicios comerciales de distribución; alojamiento, servicios de suministro de comidas y bebidas; servicios de transporte; y servicios de distribución de electricidad, gas y agua | E157: 7 | F157: Otros servicios | G157: 3 | H157: No bioeconomía | I157: 1 | J157: Culturales
A158: 157 | B158: Servicios de intermediación financiera | C158: ="7" -> 7 | D158: ="Servicios financieros y servicios conexos; servicios inmobiliarios; y servicios de alquiler y arrendamiento" -> Servicios financieros y servicios conexos; servicios inmobiliarios; y servicios de alquiler y arrendamiento | E158: 7 | F158: Otros servicios | G158: 3 | H158: No bioeconomía | I158: 2 | J158: No culturales
A159: 158 | B159: Servicios de intermediación financiera medidos indirectamente (SIFMI) | C159: ="7" -> 7 | D159: ="Servicios financieros y servicios conexos; servicios inmobiliarios; y servicios de alquiler y arrendamiento" -> Servicios financieros y servicios conexos; servicios inmobiliarios; y servicios de alquiler y arrendamiento | E159: 7 | F159: Otros servicios | G159: 3 | H159: No bioeconomía | I159: 2 | J159: No culturales
A160: 159 | B160: Servicios de seguros de vida | C160: ="7" -> 7 | D160: ="Servicios financieros y servicios conexos; servicios inmobiliarios; y servicios de alquiler y arrendamiento" -> Servicios financieros y servicios conexos; servicios inmobiliarios; y servicios de alquiler y arrendamiento | E160: 7 | F160: Otros servicios | G160: 3 | H160: No bioeconomía | I160: 2 | J160: No culturales
A161: 160 | B161: Servicios de seguros generales | C161: ="7" -> 7 | D161: ="Servicios financieros y servicios conexos; servicios inmobiliarios; y servicios de alquiler y arrendamiento" -> Servicios financieros y servicios conexos; servicios inmobiliarios; y servicios de alquiler y arrendamiento | E161: 7 | F161: Otros servicios | G161: 3 | H161: No bioeconomía | I161: 2 | J161: No culturales
A162: 161 | B162: Servicios auxiliares de intermediación financiera | C162: ="7" -> 7 | D162: ="Servicios financieros y servicios conexos; servicios inmobiliarios; y servicios de alquiler y arrendamiento" -> Servicios financieros y servicios conexos; servicios inmobiliarios; y servicios de alquiler y arrendamiento | E162: 7 | F162: Otros servicios | G162: 3 | H162: No bioeconomía | I162: 2 | J162: No culturales
A163: 162 | B163: Servicios inmobiliarios | C163: ="7" -> 7 | D163: ="Servicios financieros y servicios conexos; servicios inmobiliarios; y servicios de alquiler y arrendamiento" -> Servicios financieros y servicios conexos; servicios inmobiliarios; y servicios de alquiler y arrendamiento | E163: 7 | F163: Otros servicios | G163: 3 | H163: No bioeconomía | I163: 2 | J163: No culturales
A164: 163 | B164: Servicios de vivienda | C164: ="7" -> 7 | D164: ="Servicios financieros y servicios conexos; servicios inmobiliarios; y servicios de alquiler y arrendamiento" -> Servicios financieros y servicios conexos; servicios inmobiliarios; y servicios de alquiler y arrendamiento | E164: 7 | F164: Otros servicios | G164: 3 | H164: No bioeconomía | I164: 2 | J164: No culturales
A165: 164 | B165: Servicios jurídicos y contables | C165: ="8" -> 8 | D165: ="Servicios prestados a las empresas y servicios de producción" -> Servicios prestados a las empresas y servicios de producción | E165: 7 | F165: Otros servicios | G165: 3 | H165: No bioeconomía | I165: 2 | J165: No culturales
A166: 165 | B166: Servicios de arquitectura e ingeniería | C166: ="8" -> 8 | D166: ="Servicios prestados a las empresas y servicios de producción" -> Servicios prestados a las empresas y servicios de producción | E166: 7 | F166: Otros servicios | G166: 3 | H166: No bioeconomía | I166: 1 | J166: Culturales
A167: 166 | B167: Servicios de publicidad e investigación de mercados | C167: ="8" -> 8 | D167: ="Servicios prestados a las empresas y servicios de producción" -> Servicios prestados a las empresas y servicios de producción | E167: 7 | F167: Otros servicios | G167: 3 | H167: No bioeconomía | I167: 1 | J167: Culturales
A168: 167 | B168: Investigación y desarrollo | C168: ="8" -> 8 | D168: ="Servicios prestados a las empresas y servicios de producción" -> Servicios prestados a las empresas y servicios de producción | E168: 7 | F168: Otros servicios | G168: 2 | H168: Bioeconomía extendida | I168: 1 | J168: Culturales
...

Sheet Productos sin C
A1: Código Productos (CUP) | B1: Productos (CUP) | C1: Código CPC Grupos | D1: CPC Grupos | E1: Código Productos Compactos | F1: Productos Compactos | G1: Código Bioeconomía Productos | H1: Bioeconomía Productos | I1: Código CUPc | J1: CUPc
A2: 1 | B2: Trigo | C2: ="0" -> 0 | D2: ="Productos de la agricultura, la silvicultura y la pesca" -> Productos de la agricultura, la silvicultura y la pesca | E2: 1 | F2: Agropecuarios | G2: 1 | H2: Bioeconomía
A3: 2 | B3: Maíz | C3: ="0" -> 0 | D3: ="Productos de la agricultura, la silvicultura y la pesca" -> Productos de la agricultura, la silvicultura y la pesca | E3: 1 | F3: Agropecuarios | G3: 1 | H3: Bioeconomía
A4: 3 | B4: Otros cereales | C4: ="0" -> 0 | D4: ="Productos de la agricultura, la silvicultura y la pesca" -> Productos de la agricultura, la silvicultura y la pesca | E4: 1 | F4: Agropecuarios | G4: 1 | H4: Bioeconomía
A5: 4 | B5: Tubérculos y legumbres | C5: ="0" -> 0 | D5: ="Productos de la agricultura, la silvicultura y la pesca" -> Productos de la agricultura, la silvicultura y la pesca | E5: 1 | F5: Agropecuarios | G5: 1 | H5: Bioeconomía
A6: 5 | B6: Forrajeras y otros cultivos de uso industrial | C6: ="0" -> 0 | D6: ="Productos de la agricultura, la silvicultura y la pesca" -> Productos de la agricultura, la silvicultura y la pesca | E6: 1 | F6: Agropecuarios | G6: 1 | H6: Bioeconomía
A7: 6 | B7: Hortalizas y setas | C7: ="0" -> 0 | D7: ="Productos de la agricultura, la silvicultura y la pesca" -> Productos de la agricultura, la silvicultura y la pesca | E7: 1 | F7: Agropecuarios | G7: 1 | H7: Bioeconomía
A8: 7 | B8: Uva vinífera y pisquera | C8: ="0" -> 0 | D8: ="Productos de la agricultura, la silvicultura y la pesca" -> Productos de la agricultura, la silvicultura y la pesca | E8: 1 | F8: Agropecuarios | G8: 1 | H8: Bioeconomía
A9: 8 | B9: Uva de mesa | C9: ="0" -> 0 | D9: ="Productos de la agricultura, la silvicultura y la pesca" -> Productos de la agricultura, la silvicultura y la pesca | E9: 1 | F9: Agropecuarios | G9: 1 | H9: Bioeconomía
A10: 9 | B10: Manzanas | C10: ="0" -> 0 | D10: ="Productos de la agricultura, la silvicultura y la pesca" -> Productos de la agricultura, la silvicultura y la pesca | E10: 1 | F10: Agropecuarios | G10: 1 | H10: Bioeconomía
A11: 10 | B11: Duraznos y otros carozos | C11: ="0" -> 0 | D11: ="Productos de la agricultura, la silvicultura y la pesca" -> Productos de la agricultura, la silvicultura y la pesca | E11: 1 | F11: Agropecuarios | G11: 1 | H11: Bioeconomía
A12: 11 | B12: Paltas | C12: ="0" -> 0 | D12: ="Productos de la agricultura, la silvicultura y la pesca" -> Productos de la agricultura, la silvicultura y la pesca | E12: 1 | F12: Agropecuarios | G12: 1 | H12: Bioeconomía
A13: 12 | B13: Kiwis y otras frutas tropicales | C13: ="0" -> 0 | D13: ="Productos de la agricultura, la silvicultura y la pesca" -> Productos de la agricultura, la silvicultura y la pesca | E13: 1 | F13: Agropecuarios | G13: 1 | H13: Bioeconomía
... A27: 26 | B27: Otros pescados, mariscos y algas | C27: ="0" -> 0 | D27: ="Productos de la agricultura, la silvicultura y la pesca" -> Productos de la agricultura, la silvicultura y la pesca | E27: 1 | F27: Agropecuarios | G27: 1 | H27: Bioeconomía
A28: 27 | B28: Carbón | C28: ="1" -> 1 | D28: ="Minerales; electricidad, gas y agua" -> Minerales; electricidad, gas y agua | E28: 2 | F28: Minería | G28: 3 | H28: No bioeconomía
A29: 28 | B29: Petróleo crudo | C29: ="1" -> 1 | D29: ="Minerales; electricidad, gas y agua" -> Minerales; electricidad, gas y agua | E29: 2 | F29: Minería | G29: 3 | H29: No bioeconomía
A30: 29 | B30: Gas natural | C30: ="1" -> 1 | D30: ="Minerales; electricidad, gas y agua" -> Minerales; electricidad, gas y agua | E30: 2 | F30: Minería | G30: 3 | H30: No bioeconomía
A31: 30 | B31: Cobre | C31: ="1" -> 1 | D31: ="Minerales; electricidad, gas y agua" -> Minerales; electricidad, gas y agua | E31: 2 | F31: Minería | G31: 3 | H31: No bioeconomía
A32: 31 | B32: Minerales de molibdeno y sus concentrados | C32: ="1" -> 1 | D32: ="Minerales; electricidad, gas y agua" -> Minerales; electricidad, gas y agua | E32: 2 | F32: Minería | G32: 3 | H32: No bioeconomía
A33: 32 | B33: Hierro | C33: ="1" -> 1 | D33: ="Minerales; electricidad, gas y agua" -> Minerales; electricidad, gas y agua | E33: 2 | F33: Minería | G33: 3 | H33: No bioeconomía
A34: 33 | B34: Oro | C34: ="1" -> 1 | D34: ="Minerales; electricidad, gas y agua" -> Minerales; electricidad, gas y agua | E34: 2 | F34: Minería | G34: 3 | H34: No bioeconomía
A35: 34 | B35: Plata y otros metalíferos no ferrosos | C35: ="1" -> 1 | D35: ="Minerales; electricidad, gas y agua" -> Minerales; electricidad, gas y agua | E35: 2 | F35: Minería | G35: 3 | H35: No bioeconomía
A36: 35 | B36: Minerales no metálicos | C36: ="1" -> 1 | D36: ="Minerales; electricidad, gas y agua" -> Minerales; electricidad, gas y agua | E36: 2 | F36: Minería | G36: 3 | H36: No bioeconomía
A37: 36 | B37: Servicios de exploración minera | C37: ="1" -> 1 | D37: ="Minerales; electricidad, gas y agua" -> Minerales; electricidad, gas y agua | E37: 2 | F37: Minería | G37: 3 | H37: No bioeconomía
A38: 37 | B38: Carne de bovino | C38: ="2" -> 2 | D38: ="Productos alimenticios, bebidas y tabaco; textiles, prendas de vestir y productos de cuero" -> Productos alimenticios, bebidas y tabaco; textiles, prendas de vestir y productos de cuero | E38: 3 | F38: Manufacturas | G38: 1 | H38: Bioeconomía
A39: 38 | B39: Carne de porcino | C39: ="2" -> 2 | D39: ="Productos alimenticios, bebidas y tabaco; textiles, prendas de vestir y productos de cuero" -> Productos alimenticios, bebidas y tabaco; textiles, prendas de vestir y productos de cuero | E39: 3 | F39: Manufacturas | G39: 1 | H39: Bioeconomía
A40: 39 | B40: Carne de ave | C40: ="2" -> 2 | D40: ="Productos alimenticios, bebidas y tabaco; textiles, prendas de vestir y productos de cuero" -> Productos alimenticios, bebidas y tabaco; textiles, prendas de vestir y productos de cuero | E40: 3 | F40: Manufacturas | G40: 1 | H40: Bioeconomía
A41: 40 | B41: Cecinas y otras carnes | C41: ="2" -> 2 | D41: ="Productos alimenticios, bebidas y tabaco; textiles, prendas de vestir y productos de cuero" -> Productos alimenticios, bebidas y tabaco; textiles, prendas de vestir y productos de cuero | E41: 3 | F41: Manufacturas | G41: 1 | H41: Bioeconomía
A42: 41 | B42: Harina de pescado | C42: ="2" -> 2 | D42: ="Productos alimenticios, bebidas y tabaco; textiles, prendas de vestir y productos de cuero" -> Productos alimenticios, bebidas y tabaco; textiles, prendas de vestir y productos de cuero | E42: 3 | F42: Manufacturas | G42: 1 | H42: Bioeconomía
A43: 42 | B43: Aceite de pescado | C43: ="2" -> 2 | D43: ="Productos alimenticios, bebidas y tabaco; textiles, prendas de vestir y productos de cuero" -> Productos alimenticios, bebidas y tabaco; textiles, prendas de vestir y productos de cuero | E43: 3 | F43: Manufacturas | G43: 1 | H43: Bioeconomía
A44: 43 | B44: Salmon y trucha refrigerados o congelados | C44: ="2" -> 2 | D44: ="Productos alimenticios, bebidas y tabaco; textiles, prendas de vestir y productos de cuero" -> Productos alimenticios, bebidas y tabaco; textiles, prendas de vestir y productos de cuero | E44: 3 | F44: Manufacturas | G44: 1 | H44: Bioeconomía
A45: 44 | B45: Otros pescados refrigerados o congelados | C45: ="2" -> 2 | D45: ="Productos alimenticios, bebidas y tabaco; textiles, prendas de vestir y productos de cuero" -> Productos alimenticios, bebidas y tabaco; textiles, prendas de vestir y productos de cuero | E45: 3 | F45: Manufacturas | G45: 1 | H45: Bioeconomía
A46: 45 | B46: Conservas de pescados y mariscos | C46: ="2" -> 2 | D46: ="Productos alimenticios, bebidas y tabaco; textiles, prendas de vestir y productos de cuero" -> Productos alimenticios, bebidas y tabaco; textiles, prendas de vestir y productos de cuero | E46: 3 | F46: Manufacturas | G46: 1 | H46: Bioeconomía
A47: 46 | B47: Conservas de frutas y vegetales | C47: ="2" -> 2 | D47: ="Productos alimenticios, bebidas y tabaco; textiles, prendas de vestir y productos de cuero" -> Productos alimenticios, bebidas y tabaco; textiles, prendas de vestir y productos de cuero | E47: 3 | F47: Manufacturas | G47: 1 | H47: Bioeconomía
A48: 47 | B48: Otros aceites y grasas | C48: ="2" -> 2 | D48: ="Productos alimenticios, bebidas y tabaco; textiles, prendas de vestir y productos de cuero" -> Productos alimenticios, bebidas y tabaco; textiles, prendas de vestir y productos de cuero | E48: 3 | F48: Manufacturas | G48: 1 | H48: Bioeconomía
A49: 48 | B49: Leche elaborada | C49: ="2" -> 2 | D49: ="Productos alimenticios, bebidas y tabaco; textiles, prendas de vestir y productos de cuero" -> Productos alimenticios, bebidas y tabaco; textiles, prendas de vestir y productos de cuero | E49: 3 | F49: Manufacturas | G49: 1 | H49: Bioeconomía
... A68: 67 | B68: Calzado | C68: ="2" -> 2 | D68: ="Productos alimenticios, bebidas y tabaco; textiles, prendas de vestir y productos de cuero" -> Productos alimenticios, bebidas y tabaco; textiles, prendas de vestir y productos de cuero | E68: 3 | F68: Manufacturas | G68: 2 | H68: Bioeconomía extendida
A69: 68 | B69: Madera aserrada, cepillada y astillada | C69: ="3" -> 3 | D69: ="Otros bienes transportables, excepto productos metálicos, maquinaria y equipo" -> Otros bienes transportables, excepto productos metálicos, maquinaria y equipo | E69: 3 | F69: Manufacturas | G69: 2 | H69: Bioeconomía extendida
A70: 69 | B70: Tableros y madera prensada | C70: ="3" -> 3 | D70: ="Otros bienes transportables, excepto productos metálicos, maquinaria y equipo" -> Otros bienes transportables, excepto productos metálicos, maquinaria y equipo | E70: 3 | F70: Manufacturas | G70: 2 | H70: Bioeconomía extendida
A71: 70 | B71: Otros productos de madera | C71: ="3" -> 3 | D71: ="Otros bienes transportables, excepto productos metálicos, maquinaria y equipo" -> Otros bienes transportables, excepto productos metálicos, maquinaria y equipo | E71: 3 | F71: Manufacturas | G71: 2 | H71: Bioeconomía extendida
A72: 71 | B72: Celulosa | C72: ="3" -> 3 | D72: ="Otros bienes transportables, excepto productos metálicos, maquinaria y equipo" -> Otros bienes transportables, excepto productos metálicos, maquinaria y equipo | E72: 3 | F72: Manufacturas | G72: 2 | H72: Bioeconomía extendida
A73: 72 | B73: Papel periódico | C73: ="3" -> 3 | D73: ="Otros bienes transportables, excepto productos metálicos, maquinaria y equipo" -> Otros bienes transportables, excepto productos metálicos, maquinaria y equipo | E73: 3 | F73: Manufacturas | G73: 2 | H73: Bioeconomía extendida
A74: 73 | B74: Envases de papel y cartón | C74: ="3" -> 3 | D74: ="Otros bienes transportables, excepto productos metálicos, maquinaria y equipo" -> Otros bienes transportables, excepto productos metálicos, maquinaria y equipo | E74: 3 | F74: Manufacturas | G74: 2 | H74: Bioeconomía extendida
A75: 74 | B75: Productos tissue | C75: ="3" -> 3 | D75: ="Otros bienes transportables, excepto productos metálicos, maquinaria y equipo" -> Otros bienes transportables, excepto productos metálicos, maquinaria y equipo | E75: 3 | F75: Manufacturas | G75: 2 | H75: Bioeconomía extendida
A76: 75 | B76: Otros papeles y cartones | C76: ="3" -> 3 | D76: ="Otros bienes transportables, excepto productos metálicos, maquinaria y equipo" -> Otros bienes transportables, excepto productos metálicos, maquinaria y equipo | E76: 3 | F76: Manufacturas | G76: 2 | H76: Bioeconomía extendida
A77: 76 | B77: Libros, diarios, revistas y otros impresos | C77: ="3" -> 3 | D77: ="Otros bienes transportables, excepto productos metálicos, maquinaria y equipo" -> Otros bienes transportables, excepto productos metálicos, maquinaria y equipo | E77: 3 | F77: Manufacturas | G77: 3 | H77: No bioeconomía
A78: 77 | B78: Diésel | C78: ="3" -> 3 | D78: ="Otros bienes transportables, excepto productos metálicos, maquinaria y equipo" -> Otros bienes transportables, excepto productos metálicos, maquinaria y equipo | E78: 3 | F78: Manufacturas | G78: 3 | H78: No bioeconomía
A79: 78 | B79: Gasolinas | C79: ="3" -> 3 | D79: ="Otros bienes transportables, excepto productos metálicos, maquinaria y equipo" -> Otros bienes transportables, excepto productos metálicos, maquinaria y equipo | E79: 3 | F79: Manufacturas | G79: 3 | H79: No bioeconomía
A80: 79 | B80: Kerosene | C80: ="3" -> 3 | D80: ="Otros bienes transportables, excepto productos metálicos, maquinaria y equipo" -> Otros bienes transportables, excepto productos metálicos, maquinaria y equipo | E80: 3 | F80: Manufacturas | G80: 3 | H80: No bioeconomía
... A98: 97 | B98: Otros productos de minerales no metálicos | C98: ="3" -> 3 | D98: ="Otros bienes transportables, excepto productos metálicos, maquinaria y equipo" -> Otros bienes transportables, excepto productos metálicos, maquinaria y equipo | E98: 3 | F98: Manufacturas | G98: 3 | H98: No bioeconomía
A99: 98 | B99: Ferromolibdeno y otros productos básicos de acero | C99: ="4" -> 4 | D99: ="Productos metálicos, maquinaria y equipo" -> Productos metálicos, maquinaria y equipo | E99: 3 | F99: Manufacturas | G99: 3 | H99: No bioeconomía
A100: 99 | B100: Productos de hierro y acero | C100: ="4" -> 4 | D100: ="Productos metálicos, maquinaria y equipo" -> Productos metálicos, maquinaria y equipo | E100: 3 | F100: Manufacturas | G100: 3 | H100: No bioeconomía
A101: 100 | B101: Productos básicos de metales no ferrosos | C101: ="4" -> 4 | D101: ="Productos metálicos, maquinaria y equipo" -> Productos metálicos, maquinaria y equipo | E101: 3 | F101: Manufacturas | G101: 3 | H101: No bioeconomía
A102: 101 | B102: Productos metálicos de uso estructural | C102: ="4" -> 4 | D102: ="Productos metálicos, maquinaria y equipo" -> Productos metálicos, maquinaria y equipo | E102: 3 | F102: Manufacturas | G102: 3 | H102: No bioeconomía
A103: 102 | B103: Otros productos metálicos | C103: ="4" -> 4 | D103: ="Productos metálicos, maquinaria y equipo" -> Productos metálicos, maquinaria y equipo | E103: 3 | F103: Manufacturas | G103: 3 | H103: No bioeconomía
A104: 103 | B104: Maquinaria para uso industrial | C104: ="4" -> 4 | D104: ="Productos metálicos, maquinaria y equipo" -> Productos metálicos, maquinaria y equipo | E104: 3 | F104: Manufacturas | G104: 3 | H104: No bioeconomía
A105: 104 | B105: Computadores y sus componentes | C105: ="4" -> 4 | D105: ="Productos metálicos, maquinaria y equipo" -> Productos metálicos, maquinaria y equipo | E105: 3 | F105: Manufacturas | G105: 3 | H105: No bioeconomía
A106: 105 | B106: Otras maquinarias de oficina | C106: ="4" -> 4 | D106: ="Productos metálicos, maquinaria y equipo" -> Productos metálicos, maquinaria y equipo | E106: 3 | F106: Manufacturas | G106: 3 | H106: No bioeconomía
A107: 106 | B107: Televisores | C107: ="4" -> 4 | D107: ="Productos metálicos, maquinaria y equipo" -> Productos metálicos, maquinaria y equipo | E107: 3 | F107: Manufacturas | G107: 3 | H107: No bioeconomía
A108: 107 | B108: Teléfonos móviles | C108: ="4" -> 4 | D108: ="Productos metálicos, maquinaria y equipo" -> Productos metálicos, maquinaria y equipo | E108: 3 | F108: Manufacturas | G108: 3 | H108: No bioeconomía
A109: 108 | B109: Máquinas y aparatos de uso doméstico | C109: ="4" -> 4 | D109: ="Productos metálicos, maquinaria y equipo" -> Productos metálicos, maquinaria y equipo | E109: 3 | F109: Manufacturas | G109: 3 | H109: No bioeconomía
A110: 109 | B110: Otras maquinarias y equipos eléctricos | C110: ="4" -> 4 | D110: ="Productos metálicos, maquinaria y equipo" -> Productos metálicos, maquinaria y equipo | E110: 3 | F110: Manufacturas | G110: 3 | H110: No bioeconomía
... A119: 118 | B119: Servicios de mantenimiento y reparación de equipo de transporte | C119: ="4" -> 4 | D119: ="Productos metálicos, maquinaria y equipo" -> Productos metálicos, maquinaria y equipo | E119: 3 | F119: Manufacturas | G119: 3 | H119: No bioeconomía
A120: 119 | B120: Energía y potencia eléctrica | C120: ="1" -> 1 | D120: ="Minerales; electricidad, gas y agua" -> Minerales; electricidad, gas y agua | E120: 4 | F120: Servicios básicos | G120: 3 | H120: No bioeconomía
A121: 120 | B121: Servicios de transmisión de electricidad | C121: ="1" -> 1 | D121: ="Minerales; electricidad, gas y agua" -> Minerales; electricidad, gas y agua | E121: 4 | F121: Servicios básicos | G121: 3 | H121: No bioeconomía
A122: 121 | B122: Servicios de distribución de electricidad | C122: ="1" -> 1 | D122: ="Minerales; electricidad, gas y agua" -> Minerales; electricidad, gas y agua | E122: 4 | F122: Servicios básicos | G122: 3 | H122: No bioeconomía
A123: 122 | B123: Gas distribuido por ductos | C123: ="1" -> 1 | D123: ="Minerales; electricidad, gas y agua" -> Minerales; electricidad, gas y agua | E123: 4 | F123: Servicios básicos | G123: 3 | H123: No bioeconomía
A124: 123 | B124: Agua | C124: ="1" -> 1 | D124: ="Minerales; electricidad, gas y agua" -> Minerales; electricidad, gas y agua | E124: 4 | F124: Servicios básicos | G124: 2 | H124: Bioeconomía extendida
A125: 124 | B125: Servicios de eliminación de desperdicios y reciclaje | C125: ="1" -> 1 | D125: ="Minerales; electricidad, gas y agua" -> Minerales; electricidad, gas y agua | E125: 4 | F125: Servicios básicos | G125: 2 | H125: Bioeconomía extendida
A126: 125 | B126: Edificios residenciales | C126: ="5" -> 5 | D126: ="Construcciones y servicios de construcción" -> Construcciones y servicios de construcción | E126: 5 | F126: Construcción | G126: 3 | H126: No bioeconomía
A127: 126 | B127: Edificios no residenciales | C127: ="5" -> 5 | D127: ="Construcciones y servicios de construcción" -> Construcciones y servicios de construcción | E127: 5 | F127: Construcción | G127: 3 | H127: No bioeconomía
A128: 127 | B128: Obras viales | C128: ="5" -> 5 | D128: ="Construcciones y servicios de construcción" -> Construcciones y servicios de construcción | E128: 5 | F128: Construcción | G128: 3 | H128: No bioeconomía
A129: 128 | B129: Obras de proyectos de energía eléctrica | C129: ="5" -> 5 | D129: ="Construcciones y servicios de construcción" -> Construcciones y servicios de construcción | E129: 5 | F129: Construcción | G129: 3 | H129: No bioeconomía
A130: 129 | B130: Obras mineras | C130: ="5" -> 5 | D130: ="Construcciones y servicios de construcción" -> Construcciones y servicios de construcción | E130: 5 | F130: Construcción | G130: 3 | H130: No bioeconomía
A131: 130 | B131: Otras obras de ingeniería | C131: ="5" -> 5 | D131: ="Construcciones y servicios de construcción" -> Construcciones y servicios de construcción | E131: 5 | F131: Construcción | G131: 3 | H131: No bioeconomía
A132: 131 | B132: Servicios de construcción | C132: ="5" -> 5 | D132: ="Construcciones y servicios de construcción" -> Construcciones y servicios de construcción | E132: 5 | F132: Construcción | G132: 3 | H132: No bioeconomía
A133: 132 | B133: Servicios comerciales de intermediación automotriz | C133: ="6" -> 6 | D133: ="Servicios comerciales de distribución; alojamiento, servicios de suministro de comidas y bebidas; servicios de transporte; y servicios de distribución de electricidad, gas y agua" -> Servicios comerciales de distribución; alojamiento, servicios de suministro de comidas y bebidas; servicios de transporte; y servicios de distribución de electricidad, gas y agua | E133: 6 | F133: Comercio | G133: 3 | H133: No bioeconomía
A134: 133 | B134: Servicios comerciales de intermediación mayorista | C134: ="6" -> 6 | D134: ="Servicios comerciales de distribución; alojamiento, servicios de suministro de comidas y bebidas; servicios de transporte; y servicios de distribución de electricidad, gas y agua" -> Servicios comerciales de distribución; alojamiento, servicios de suministro de comidas y bebidas; servicios de transporte; y servicios de distribución de electricidad, gas y agua | E134: 6 | F134: Comercio | G134: 3 | H134: No bioeconomía
A135: 134 | B135: Servicios comerciales de intermediación minorista | C135: ="6" -> 6 | D135: ="Servicios comerciales de distribución; alojamiento, servicios de suministro de comidas y bebidas; servicios de transporte; y servicios de distribución de electricidad, gas y agua" -> Servicios comerciales de distribución; alojamiento, servicios de suministro de comidas y bebidas; servicios de transporte; y servicios de distribución de electricidad, gas y agua | E135: 6 | F135: Comercio | G135: 3 | H135: No bioeconomía
A136: 135 | B136: Servicios comerciales a cambio de una retribución o por contrata | C136: ="6" -> 6 | D136: ="Servicios comerciales de distribución; alojamiento, servicios de suministro de comidas y bebidas; servicios de transporte; y servicios de distribución de electricidad, gas y agua" -> Servicios comerciales de distribución; alojamiento, servicios de suministro de comidas y bebidas; servicios de transporte; y servicios de distribución de electricidad, gas y agua | E136: 6 | F136: Comercio | G136: 3 | H136: No bioeconomía
A137: 136 | B137: Servicios de mantenimiento y reparación de vehículos automotores | C137: ="6" -> 6 | D137: ="Servicios comerciales de distribución; alojamiento, servicios de suministro de comidas y bebidas; servicios de transporte; y servicios de distribución de electricidad, gas y agua" -> Servicios comerciales de distribución; alojamiento, servicios de suministro de comidas y bebidas; servicios de transporte; y servicios de distribución de electricidad, gas y agua | E137: 7 | F137: Otros servicios | G137: 3 | H137: No bioeconomía
A138: 137 | B138: Servicios de hotelería | C138: ="6" -> 6 | D138: ="Servicios comerciales de distribución; alojamiento, servicios de suministro de comidas y bebidas; servicios de transporte; y servicios de distribución de electricidad, gas y agua" -> Servicios comerciales de distribución; alojamiento, servicios de suministro de comidas y bebidas; servicios de transporte; y servicios de distribución de electricidad, gas y agua | E138: 7 | F138: Otros servicios | G138: 3 | H138: No bioeconomía
A139: 138 | B139: Servicios de restaurantes | C139: ="6" -> 6 | D139: ="Servicios comerciales de distribución; alojamiento, servicios de suministro de comidas y bebidas; servicios de transporte; y servicios de distribución de electricidad, gas y agua" -> Servicios comerciales de distribución; alojamiento, servicios de suministro de comidas y bebidas; servicios de transporte; y servicios de distribución de electricidad, gas y agua | E139: 7 | F139: Otros servicios | G139: 2 | H139: Bioeconomía extendida
A140: 139 | B140: Servicios de transporte por ferrocarril | C140: ="6" -> 6 | D140: ="Servicios comerciales de distribución; alojamiento, servicios de suministro de comidas y bebidas; servicios de transporte; y servicios de distribución de electricidad, gas y agua" -> Servicios comerciales de distribución; alojamiento, servicios de suministro de comidas y bebidas; servicios de transporte; y servicios de distribución de electricidad, gas y agua | E140: 7 | F140: Otros servicios | G140: 3 | H140: No bioeconomía
A141: 140 | B141: Servicios de transporte caminero de pasajeros | C141: ="6" -> 6 | D141: ="Servicios comerciales de distribución; alojamiento, servicios de suministro de comidas y bebidas; servicios de transporte; y servicios de distribución de electricidad, gas y agua" -> Servicios comerciales de distribución; alojamiento, servicios de suministro de comidas y bebidas; servicios de transporte; y servicios de distribución de electricidad, gas y agua | E141: 7 | F141: Otros servicios | G141: 3 | H141: No bioeconomía
A142: 141 | B142: Servicios de transporte caminero de carga | C142: ="6" -> 6 | D142: ="Servicios comerciales de distribución; alojamiento, servicios de suministro de comidas y bebidas; servicios de transporte; y servicios de distribución de electricidad, gas y agua" -> Servicios comerciales de distribución; alojamiento, servicios de suministro de comidas y bebidas; servicios de transporte; y servicios de distribución de electricidad, gas y agua | E142: 7 | F142: Otros servicios | G142: 3 | H142: No bioeconomía
A143: 142 | B143: Transporte por tuberías (gasoductos y oleoductos) | C143: ="6" -> 6 | D143: ="Servicios comerciales de distribución; alojamiento, servicios de suministro de comidas y bebidas; servicios de transporte; y servicios de distribución de electricidad, gas y agua" -> Servicios comerciales de distribución; alojamiento, servicios de suministro de comidas y bebidas; servicios de transporte; y servicios de distribución de electricidad, gas y agua | E143: 7 | F143: Otros servicios | G143: 3 | H143: No bioeconomía
A144: 143 | B144: Servicios de transporte marítimo | C144: ="6" -> 6 | D144: ="Servicios comerciales de distribución; alojamiento, servicios de suministro de comidas y bebidas; servicios de transporte; y servicios de distribución de electricidad, gas y agua" -> Servicios comerciales de distribución; alojamiento, servicios de suministro de comidas y bebidas; servicios de transporte; y servicios de distribución de electricidad, gas y agua | E144: 7 | F144: Otros servicios | G144: 3 | H144: No bioeconomía
... A157: 156 | B157: Servicios de edición, producción y difusión | C157: ="6" -> 6 | D157: ="Servicios comerciales de distribución; alojamiento, servicios de suministro de comidas y bebidas; servicios de transporte; y servicios de distribución de electricidad, gas y agua" -> Servicios comerciales de distribución; alojamiento, servicios de suministro de comidas y bebidas; servicios de transporte; y servicios de distribución de electricidad, gas y agua | E157: 7 | F157: Otros servicios | G157: 3 | H157: No bioeconomía
A158: 157 | B158: Servicios de intermediación financiera | C158: ="7" -> 7 | D158: ="Servicios financieros y servicios conexos; servicios inmobiliarios; y servicios de alquiler y arrendamiento" -> Servicios financieros y servicios conexos; servicios inmobiliarios; y servicios de alquiler y arrendamiento | E158: 7 | F158: Otros servicios | G158: 3 | H158: No bioeconomía
A159: 158 | B159: Servicios de intermediación financiera medidos indirectamente (SIFMI) | C159: ="7" -> 7 | D159: ="Servicios financieros y servicios conexos; servicios inmobiliarios; y servicios de alquiler y arrendamiento" -> Servicios financieros y servicios conexos; servicios inmobiliarios; y servicios de alquiler y arrendamiento | E159: 7 | F159: Otros servicios | G159: 3 | H159: No bioeconomía
A160: 159 | B160: Servicios de seguros de vida | C160: ="7" -> 7 | D160: ="Servicios financieros y servicios conexos; servicios inmobiliarios; y servicios de alquiler y arrendamiento" -> Servicios financieros y servicios conexos; servicios inmobiliarios; y servicios de alquiler y arrendamiento | E160: 7 | F160: Otros servicios | G160: 3 | H160: No bioeconomía
A161: 160 | B161: Servicios de seguros generales | C161: ="7" -> 7 | D161: ="Servicios financieros y servicios conexos; servicios inmobiliarios; y servicios de alquiler y arrendamiento" -> Servicios financieros y servicios conexos; servicios inmobiliarios; y servicios de alquiler y arrendamiento | E161: 7 | F161: Otros servicios | G161: 3 | H161: No bioeconomía
A162: 161 | B162: Servicios auxiliares de intermediación financiera | C162: ="7" -> 7 | D162: ="Servicios financieros y servicios conexos; servicios inmobiliarios; y servicios de alquiler y arrendamiento" -> Servicios financieros y servicios conexos; servicios inmobiliarios; y servicios de alquiler y arrendamiento | E162: 7 | F162: Otros servicios | G162: 3 | H162: No bioeconomía
A163: 162 | B163: Servicios inmobiliarios | C163: ="7" -> 7 | D163: ="Servicios financieros y servicios conexos; servicios inmobiliarios; y servicios de alquiler y arrendamiento" -> Servicios financieros y servicios conexos; servicios inmobiliarios; y servicios de alquiler y arrendamiento | E163: 7 | F163: Otros servicios | G163: 3 | H163: No bioeconomía
A164: 163 | B164: Servicios de vivienda | C164: ="7" -> 7 | D164: ="Servicios financieros y servicios conexos; servicios inmobiliarios; y servicios de alquiler y arrendamiento" -> Servicios financieros y servicios conexos; servicios inmobiliarios; y servicios de alquiler y arrendamiento | E164: 7 | F164: Otros servicios | G164: 3 | H164: No bioeconomía
A165: 164 | B165: Servicios jurídicos y contables | C165: ="8" -> 8 | D165: ="Servicios prestados a las empresas y servicios de producción" -> Servicios prestados a las empresas y servicios de producción | E165: 7 | F165: Otros servicios | G165: 3 | H165: No bioeconomía
A166: 165 | B166: Servicios de arquitectura e ingeniería | C166: ="8" -> 8 | D166: ="Servicios prestados a las empresas y servicios de producción" -> Servicios prestados a las empresas y servicios de producción | E166: 7 | F166: Otros servicios | G166: 3 | H166: No bioeconomía
A167: 166 | B167: Servicios de publicidad e investigación de mercados | C167: ="8" -> 8 | D167: ="Servicios prestados a las empresas y servicios de producción" -> Servicios prestados a las empresas y servicios de producción | E167: 7 | F167: Otros servicios | G167: 3 | H167: No bioeconomía
A168: 167 | B168: Investigación y desarrollo | C168: ="8" -> 8 | D168: ="Servicios prestados a las empresas y servicios de producción" -> Servicios prestados a las empresas y servicios de producción | E168: 7 | F168: Otros servicios | G168: 2 | H168: Bioeconomía extendida
...
